VHDL/DPD.vhd
LIBRARY IEEE;
USE IEEE.std_logic_1164.ALL;
USE IEEE.numeric_std.ALL;
USE work.functions.ALL;

ENTITY DPD IS
PORT (
    clk   : IN STD_LOGIC;
    reset : IN STD_LOGIC;

    UR    : IN STD_LOGIC_VECTOR(n_bits_resolution - 1 DOWNTO 0);
    UI    : IN STD_LOGIC_VECTOR(n_bits_resolution - 1 DOWNTO 0);

    UR_out : OUT STD_LOGIC_VECTOR(n_bits_resolution - 1 DOWNTO 0);
    UI_out : OUT STD_LOGIC_VECTOR(n_bits_resolution - 1 DOWNTO 0)
);
END ENTITY;

ARCHITECTURE rtl OF DPD IS

    TYPE term_matrix_t IS ARRAY (0 TO n_signals_used - 1,
                                 0 TO n_polygnos_degree - 1)
                                 OF complex_number;

    SIGNAL x_in       : complex_number;
    SIGNAL delay_line : delay_line_t := (OTHERS => (0,0));
    SIGNAL terms      : term_matrix_t := (OTHERS => (OTHERS => (0,0)));

BEGIN

----------------------------------------------------------------------
-- INPUT
----------------------------------------------------------------------
process(clk)
begin
    if rising_edge(clk) then
        if reset = '1' then
            x_in <= (0,0);
        else
            x_in <= (
                reall => to_integer(signed(UR)),
                imag  => to_integer(signed(UI))
            );
        end if;
    end if;
end process;

----------------------------------------------------------------------
-- DELAY LINE
----------------------------------------------------------------------
process(clk)
begin
    if rising_edge(clk) then
        if reset = '1' then
            delay_line <= (OTHERS => (0,0));
        else
            delay_line(0) <= x_in;

            for i in 1 to n_signals_used-1 loop
                delay_line(i) <= delay_line(i-1);
            end loop;
        end if;
    end if;
end process;

----------------------------------------------------------------------
-- TERMS (FIXADO: SEM "*")
----------------------------------------------------------------------
gen_i: for i in 0 to n_signals_used-1 generate
    gen_j: for j in 0 to n_polygnos_degree-1 generate

        terms(i, j) <= multiplication(
            delay_line(i),
            (reall => 1, imag => 0)
        );

    end generate;
end generate;

----------------------------------------------------------------------
-- SUM
----------------------------------------------------------------------
process(clk)
    variable rsum, isum : integer := 0;
begin
    if rising_edge(clk) then
        if reset = '1' then
            UR_out <= (others => '0');
            UI_out <= (others => '0');
        else

            rsum := 0;
            isum := 0;

            for i in 0 to n_signals_used-1 loop
                for j in 0 to n_polygnos_degree-1 loop
                    rsum := rsum + terms(i, j).reall;
                    isum := isum + terms(i, j).imag;
                end loop;
            end loop;

            UR_out <= std_logic_vector(to_signed(rsum, UR_out'length));
            UI_out <= std_logic_vector(to_signed(isum, UI_out'length));

        end if;
    end if;
end process;

END ARCHITECTURE;

tb_main.vhd
--------------------------------------------------------------------------------
LIBRARY ieee;
USE ieee.std_logic_1164.ALL;
  
ENTITY tb IS
END tb;
 
ARCHITECTURE behavior OF tb IS 
    CONSTANT n_bits_resolution : INTEGER := 9;
    CONSTANT n_bits_overflow : INTEGER := 8;
    CONSTANT n_signals_used : INTEGER := 2;
    CONSTANT n_polygnos_degree : INTEGER := 2;
    -- Component Declaration for the Unit Under Test (UUT)
    COMPONENT dpd
        PORT (
            reset : IN STD_LOGIC;
            clk : IN STD_LOGIC;
            UR : IN STD_LOGIC_VECTOR(n_bits_resolution - 1 DOWNTO 0);
            UI : IN STD_LOGIC_VECTOR(n_bits_resolution - 1 DOWNTO 0);
            UR_out : OUT STD_LOGIC_VECTOR(n_bits_resolution - 1 DOWNTO 0);
            UI_out : OUT STD_LOGIC_VECTOR(n_bits_resolution - 1 DOWNTO 0)
        );
    END COMPONENT;

    -- Signals for connecting to UUT
    SIGNAL reset : STD_LOGIC := '0';
    SIGNAL clk : STD_LOGIC := '0';
    SIGNAL UR : STD_LOGIC_VECTOR(n_bits_resolution - 1 DOWNTO 0) := (OTHERS => '0');
    SIGNAL UI : STD_LOGIC_VECTOR(n_bits_resolution - 1 DOWNTO 0) := (OTHERS => '0');
    SIGNAL UR_out : STD_LOGIC_VECTOR(n_bits_resolution - 1 DOWNTO 0) := (OTHERS => '0');
    SIGNAL UI_out : STD_LOGIC_VECTOR(n_bits_resolution - 1 DOWNTO 0);

    -- Clock period definition
    CONSTANT clk_period : TIME := 10 ns;
 
BEGIN
 
	-- Instantiate the Unit Under Test (UUT)
   uut: DPD PORT MAP (
          reset => reset,
          clk => clk,
          UR => UR,
          UI => UI,
          UR_out => UR_out,
          UI_out => UI_out
        );

   -- Clock process definitions
   clk_process :process
   begin
		clk <= '0';
		wait for clk_period/2;
		clk <= '1';
		wait for clk_period/2;
   end process;
 

   -- Stimulus process
   stim_proc: process
   begin		
      -- hold reset state for 100 ns.
      wait for 100 ns;	

      wait for clk_period*10;

      -- insert stimulus here 
      wait;
   end process;

      -- in process
   calc_proc: process
   begin		
      reset <= '1';
      wait for 2 * clk_period;	
      reset <= '0';
      WAIT FOR clk_period;
      
UR <= "000111101";
UI <= "010100000";
WAIT FOR clk_period;
UR <= "000011100";
UI <= "010100101";
WAIT FOR clk_period;
UR <= "111111001";
UI <= "010100001";
WAIT FOR clk_period;
UR <= "111011010";
UI <= "010010111";
WAIT FOR clk_period;
UR <= "110111101";
UI <= "010001000";
WAIT FOR clk_period;
UR <= "110100101";
UI <= "001110100";
WAIT FOR clk_period;
UR <= "110001111";
UI <= "001011110";
WAIT FOR clk_period;
UR <= "101111110";
UI <= "001001000";
WAIT FOR clk_period;
UR <= "101110000";
UI <= "000110101";
WAIT FOR clk_period;
UR <= "101100110";
UI <= "000100100";
WAIT FOR clk_period;
UR <= "101011111";
UI <= "000011010";
WAIT FOR clk_period;
UR <= "101011011";
UI <= "000010101";
WAIT FOR clk_period;
UR <= "101011010";
UI <= "000010111";
WAIT FOR clk_period;
UR <= "101011011";
UI <= "000011100";
WAIT FOR clk_period;
UR <= "101011100";
UI <= "000100110";
WAIT FOR clk_period;
UR <= "101011110";
UI <= "000101111";
WAIT FOR clk_period;
UR <= "101100000";
UI <= "000111001";
WAIT FOR clk_period;
UR <= "101100010";
UI <= "000111110";
WAIT FOR clk_period;
UR <= "101100001";
UI <= "000111111";
WAIT FOR clk_period;
UR <= "101011111";
UI <= "000111011";
WAIT FOR clk_period;
UR <= "101011010";
UI <= "000110010";
WAIT FOR clk_period;
UR <= "101010100";
UI <= "000100101";
WAIT FOR clk_period;
UR <= "101010000";
UI <= "000010110";
WAIT FOR clk_period;
UR <= "101001011";
UI <= "000001011";
WAIT FOR clk_period;
UR <= "101000111";
UI <= "000000011";
WAIT FOR clk_period;
UR <= "101001001";
UI <= "000000001";
WAIT FOR clk_period;
UR <= "101001111";
UI <= "000001000";
WAIT FOR clk_period;
UR <= "101011011";
UI <= "000011000";
WAIT FOR clk_period;
UR <= "101101101";
UI <= "000110001";
WAIT FOR clk_period;
UR <= "110000011";
UI <= "001010000";
WAIT FOR clk_period;
UR <= "110011110";
UI <= "001110010";
WAIT FOR clk_period;
UR <= "110111101";
UI <= "010010011";
WAIT FOR clk_period;
UR <= "111011011";
UI <= "010110001";
WAIT FOR clk_period;
UR <= "111111000";
UI <= "011000101";
WAIT FOR clk_period;
UR <= "000010011";
UI <= "011001011";
WAIT FOR clk_period;
UR <= "000101000";
UI <= "011000011";
WAIT FOR clk_period;
UR <= "000111000";
UI <= "010101100";
WAIT FOR clk_period;
UR <= "001000000";
UI <= "010000111";
WAIT FOR clk_period;
UR <= "001000001";
UI <= "001010101";
WAIT FOR clk_period;
UR <= "000111100";
UI <= "000011110";
WAIT FOR clk_period;
UR <= "000101111";
UI <= "111100100";
WAIT FOR clk_period;
UR <= "000011100";
UI <= "110101101";
WAIT FOR clk_period;
UR <= "000000110";
UI <= "110000000";
WAIT FOR clk_period;
UR <= "111101111";
UI <= "101011100";
WAIT FOR clk_period;
UR <= "111010110";
UI <= "101001010";
WAIT FOR clk_period;
UR <= "110111100";
UI <= "101001001";
WAIT FOR clk_period;
UR <= "110100011";
UI <= "101010101";
WAIT FOR clk_period;
UR <= "110001111";
UI <= "101110001";
WAIT FOR clk_period;
UR <= "101111101";
UI <= "110010110";
WAIT FOR clk_period;
UR <= "101101101";
UI <= "111000001";
WAIT FOR clk_period;

      -- insert stimulus here 
      wait;
   end process;
    
END;

VHDL/output.vcd
$date
  Sat Mar 21 10:22:16 2026
$end
$version
  GHDL v0
$end
$timescale
  1 fs
$end
$scope module standard $end
$upscope $end
$scope module textio $end
$upscope $end
$scope module std_logic_1164 $end
$upscope $end
$scope module numeric_std $end
$upscope $end
$scope module std_logic_textio $end
$upscope $end
$scope module functions $end
$upscope $end
$scope module tb $end
$var reg 1 ! reset $end
$var reg 1 " clk $end
$var reg 11 # ur[10:0] $end
$var reg 11 $ ui[10:0] $end
$var reg 11 % ur_out[10:0] $end
$var reg 11 & ui_out[10:0] $end
$scope module uut $end
$var reg 1 ' clk $end
$var reg 1 ( reset $end
$var reg 11 ) ur[10:0] $end
$var reg 11 * ui[10:0] $end
$var reg 11 + ur_out[10:0] $end
$var reg 11 , ui_out[10:0] $end
$comment x_in is not handled $end
$comment delay_line is not handled $end
$comment terms is not handled $end
$scope module gen_i(0) $end
$scope module gen_j(0) $end
$upscope $end
$scope module gen_j(1) $end
$upscope $end
$scope module gen_j(2) $end
$upscope $end
$scope module gen_j(3) $end
$upscope $end
$scope module gen_j(4) $end
$upscope $end
$upscope $end
$scope module gen_i(1) $end
$scope module gen_j(0) $end
$upscope $end
$scope module gen_j(1) $end
$upscope $end
$scope module gen_j(2) $end
$upscope $end
$scope module gen_j(3) $end
$upscope $end
$scope module gen_j(4) $end
$upscope $end
$upscope $end
$scope module gen_i(2) $end
$scope module gen_j(0) $end
$upscope $end
$scope module gen_j(1) $end
$upscope $end
$scope module gen_j(2) $end
$upscope $end
$scope module gen_j(3) $end
$upscope $end
$scope module gen_j(4) $end
$upscope $end
$upscope $end
$upscope $end
$upscope $end
$enddefinitions $end
#0
1!
0"
b00000000000 #
b00000000000 $
bUUUUUUUUUUU %
bUUUUUUUUUUU &
0'
1(
b00000000000 )
b00000000000 *
bUUUUUUUUUUU +
bUUUUUUUUUUU ,
#8000000
1"
b00000000000 %
b00000000000 &
1'
b00000000000 +
b00000000000 ,
#16000000
0"
0'
#24000000
1"
1'
#32000000
0!
0"
0'
0(
#40000000
1"
1'
#48000000
0"
b00001110111 #
b11010100000 $
0'
b00001110111 )
b11010100000 *
#56000000
1"
1'
#64000000
0"
b00001111011 #
b11010011011 $
0'
b00001111011 )
b11010011011 *
#72000000
1"
1'
#80000000
0"
b00001110110 #
b11010110100 $
0'
b00001110110 )
b11010110100 *
#88000000
1"
b01001010011 %
b00100100000 &
1'
b01001010011 +
b00100100000 ,
#96000000
0"
b00001101011 #
b11011101000 $
0'
b00001101011 )
b11011101000 *
#104000000
1"
b10010111010 %
b01000100111 &
1'
b10010111010 +
b01000100111 ,
#112000000
0"
b00001011101 #
b11100110000 $
0'
b00001011101 )
b11100110000 *
#120000000
1"
b11100001000 %
b01110101011 &
1'
b11100001000 +
b01110101011 ,
#128000000
0"
b00001010000 #
b11110000100 $
0'
b00001010000 )
b11110000100 *
#136000000
1"
b11011001100 %
b10100010011 &
1'
b11011001100 +
b10100010011 ,
#144000000
0"
b00001000110 #
b11111011000 $
0'
b00001000110 )
b11111011000 *
#152000000
1"
b11000110110 %
b11111111100 &
1'
b11000110110 +
b11111111100 ,
#160000000
0"
b00001000011 #
b00000100101 $
0'
b00001000011 )
b00000100101 *
#168000000
1"
b10101111000 %
b10000001100 &
1'
b10101111000 +
b10000001100 ,
#176000000
0"
b00001001000 #
b00001100001 $
0'
b00001001000 )
b00001100001 *
#184000000
1"
b10010111111 %
b00010111100 &
1'
b10010111111 +
b00010111100 ,
#192000000
0"
b00001010100 #
b00010000110 $
0'
b00001010100 )
b00010000110 *
#200000000
1"
b10000111101 %
b10110000101 &
1'
b10000111101 +
b10110000101 ,
#208000000
0"
b00001101000 #
b00010010001 $
0'
b00001101000 )
b00010010001 *
#216000000
1"
b10000010101 %
b00111010110 &
1'
b10000010101 +
b00111010110 ,
#224000000
0"
b00010000000 #
b00010000001 $
0'
b00010000000 )
b00010000001 *
#232000000
1"
b10001011011 %
b10100111100 &
1'
b10001011011 +
b10100111100 ,
#240000000
0"
b00010011011 #
b00001011010 $
0'
b00010011011 )
b00001011010 *
#248000000
1"
b10100010100 %
b11101011000 &
1'
b10100010100 +
b11101011000 ,
#256000000
0"
b00010110111 #
b00000100001 $
0'
b00010110111 )
b00000100001 *
#264000000
1"
b11000101100 %
b11111111000 &
1'
b11000101100 +
b11111111000 ,
#272000000
0"
b00011010001 #
b11111011110 $
0'
b00011010001 )
b11111011110 *
#280000000
1"
b11110001111 %
b11100011100 &
1'
b11110001111 +
b11100011100 ,
#288000000
0"
b00011101001 #
b11110011000 $
0'
b00011101001 )
b11110011000 *
#296000000
1"
b00100011010 %
b10011101100 &
1'
b00100011010 +
b10011101100 ,
#304000000
0"
b00011111110 #
b11101010110 $
0'
b00011111110 )
b11101010110 *
#312000000
1"
b01010101111 %
b00110111101 &
1'
b01010101111 +
b00110111101 ,
#320000000
0"
b00100001111 #
b11100100000 $
0'
b00100001111 )
b11100100000 *
#328000000
1"
b10000110101 %
b10111110011 &
1'
b10000110101 +
b10111110011 ,
#336000000
0"
b00100011101 #
b11011111000 $
0'
b00100011101 )
b11011111000 *
#344000000
1"
b10110011000 %
b00111111100 &
1'
b10110011000 +
b00111111100 ,
#352000000
0"
b00100100111 #
b11011100001 $
0'
b00100100111 )
b11011100001 *
#360000000
1"
b11011001110 %
b11001000110 &
1'
b11011001110 +
b11001000110 ,
#368000000
0"
b00100101110 #
b11011011011 $
0'
b00100101110 )
b11011011011 *
#376000000
1"
b11111010010 %
b01100100110 &
1'
b11111010010 +
b01100100110 ,
#384000000
0"
b00100110000 #
b11011100011 $
0'
b00100110000 )
b11011100011 *
#392000000
1"
b00010011111 %
b00011011101 &
1'
b00010011111 +
b00011011101 ,
#400000000
0"
b00100101110 #
b11011110101 $
0'
b00100101110 )
b11011110101 *
#408000000
1"
b00100111010 %
b11110000100 &
1'
b00100111010 +
b11110000100 ,
#416000000
0"
b00100100101 #
b11100001101 $
0'
b00100100101 )
b11100001101 *
#424000000
1"
b00110011001 %
b11100011011 &
1'
b00110011001 +
b11100011011 ,
#432000000
0"
b00100010101 #
b11100101001 $
0'
b00100010101 )
b11100101001 *
#440000000
1"
b00110111100 %
b11101111111 &
1'
b00110111100 +
b11101111111 ,
#448000000
0"
b00011111101 #
b11101000110 $
0'
b00011111101 )
b11101000110 *
#456000000
1"
b00110001111 %
b00001111001 &
1'
b00110001111 +
b00001111001 ,
#464000000
0"
b00011011101 #
b11101100010 $
0'
b00011011101 )
b11101100010 *
#472000000
1"
b00100001000 %
b00111010111 &
1'
b00100001000 +
b00111010111 ,
#480000000
0"
b00010110111 #
b11110000000 $
0'
b00010110111 )
b11110000000 *
#488000000
1"
b00000010011 %
b01101101100 &
1'
b00000010011 +
b01101101100 ,
#496000000
0"
b00010001100 #
b11110100000 $
0'
b00010001100 )
b11110100000 *
#504000000
1"
b11010101011 %
b10100010101 &
1'
b11010101011 +
b10100010101 ,
#512000000
0"
b00001011111 #
b11111000110 $
0'
b00001011111 )
b11111000110 *
#520000000
1"
b10011010101 %
b11011001000 &
1'
b10011010101 +
b11011001000 ,
#528000000
0"
b00000110011 #
b11111110100 $
0'
b00000110011 )
b11111110100 *
#536000000
1"
b01010100000 %
b00010001010 &
1'
b01010100000 +
b00010001010 ,
#544000000
0"
b00000001011 #
b00000101011 $
0'
b00000001011 )
b00000101011 *
#552000000
1"
b00000101010 %
b01001111110 &
1'
b00000101010 +
b01001111110 ,
#560000000
0"
b11111101010 #
b00001101100 $
0'
b11111101010 )
b00001101100 *
#568000000
1"
b10110010110 %
b10011000010 &
1'
b10110010110 +
b10011000010 ,
#576000000
0"
b11111010000 #
b00010110101 $
0'
b11111010000 )
b00010110101 *
#584000000
1"
b01100010001 %
b11101111001 &
1'
b01100010001 +
b11101111001 ,
#592000000
0"
b11110111111 #
b00100000010 $
0'
b11110111111 )
b00100000010 *
#600000000
1"
b00011001000 %
b01010110111 &
1'
b00011001000 +
b01010110111 ,
#608000000
0"
b11110110101 #
b00101001110 $
0'
b11110110101 )
b00101001110 *
#616000000
1"
b11011011001 %
b11001111100 &
1'
b11011011001 +
b11001111100 ,
#624000000
0"
b11110101111 #
b00110010001 $
0'
b11110101111 )
b00110010001 *
#632000000
1"
b10101011101 %
b01010101111 &
1'
b10101011101 +
b01010101111 ,
#640000000
0"
b11110101011 #
b00111000011 $
0'
b11110101011 )
b00111000011 *
#648000000
1"
b10001010100 %
b11100011001 &
1'
b10001010100 +
b11100011001 ,
#656000000
0"
b11110100101 #
b00111011111 $
0'
b11110100101 )
b00111011111 *
#664000000
1"
b01110101111 %
b01101100101 &
1'
b01110101111 +
b01101100101 ,
#672000000
0"
b11110011010 #
b00111011110 $
0'
b11110011010 )
b00111011110 *
#680000000
1"
b01101001011 %
b11100101010 &
1'
b01101001011 +
b11100101010 ,
#688000000
0"
b11110000111 #
b00110111110 $
0'
b11110000111 )
b00110111110 *
#696000000
1"
b01011111011 %
b00111111111 &
1'
b01011111011 +
b00111111111 ,
#704000000
0"
b11101101011 #
b00101111111 $
0'
b11101101011 )
b00101111111 *
#712000000
1"
b01010010010 %
b01110000000 &
1'
b01010010010 +
b01110000000 ,
#720000000
0"
b11101001001 #
b00100100110 $
0'
b11101001001 )
b00100100110 *
#728000000
1"
b00111011110 %
b01101100111 &
1'
b00111011110 +
b01101100111 ,
#736000000
0"
b11100100001 #
b00010111000 $
0'
b11100100001 )
b00010111000 *
#744000000
1"
b00010111100 %
b00110000111 &
1'
b00010111100 +
b00110000111 ,
#752000000
0"
b11011111000 #
b00000111111 $
0'
b11011111000 )
b00000111111 *
#760000000
1"
b11100100111 %
b10111101111 &
1'
b11100100111 +
b10111101111 ,
#768000000
0"
b11011010011 #
b11111000101 $
0'
b11011010011 )
b11111000101 *
#776000000
1"
b10100101001 %
b00011010001 &
1'
b10100101001 +
b00011010001 ,
#784000000
0"
b11010110110 #
b11101010100 $
0'
b11010110110 )
b11101010100 *
#792000000
1"
b01011101010 %
b01010010001 &
1'
b01011101010 +
b01010010001 ,
#800000000
0"
b11010100100 #
b11011110110 $
0'
b11010100100 )
b11011110110 *
#808000000
1"
b00010011100 %
b01110101100 &
1'
b00010011100 +
b01110101100 ,
#816000000
0"
b11010100000 #
b11010110000 $
0'
b11010100000 )
b11010110000 *
#824000000
1"
b11010000101 %
b10010111000 &
1'
b11010000101 +
b10010111000 ,
#832000000
0"
b11010101011 #
b11010000111 $
0'
b11010101011 )
b11010000111 *
#840000000
1"
b10011100001 %
b11001001011 &
1'
b10011100001 +
b11001001011 ,
#848000000
0"
b11011000100 #
b11001111000 $
0'
b11011000100 )
b11001111000 *
#856000000
1"
b01111100010 %
b00011100010 &
1'
b01111100010 +
b00011100010 ,
#864000000
0"
b11011100111 #
b11010000001 $
0'
b11011100111 )
b11010000001 *
#872000000
1"
b01110101011 %
b10011100001 &
1'
b01110101011 +
b10011100001 ,
#880000000
0"
b11100010001 #
b11010011010 $
0'
b11100010001 )
b11010011010 *
#888000000
1"
b10001001011 %
b01001101011 &
1'
b10001001011 +
b01001101011 ,
#896000000
0"
b11100111100 #
b11010111010 $
0'
b11100111100 )
b11010111010 *
#904000000
1"
b10110101110 %
b00110000000 &
1'
b10110101110 +
b00110000000 ,
#912000000
0"
b11101100100 #
b11011011001 $
0'
b11101100100 )
b11011011001 *
#920000000
1"
b11110101100 %
b00111011111 &
1'
b11110101100 +
b00111011111 ,
#928000000
0"
b11110000110 #
b11011101110 $
0'
b11110000110 )
b11011101110 *
#936000000
1"
b01000000100 %
b01100101001 &
1'
b01000000100 +
b01100101001 ,
#944000000
0"
b11110100000 #
b11011110101 $
0'
b11110100000 )
b11011110101 *
#952000000
1"
b10001110101 %
b10011100001 &
1'
b10001110101 +
b10011100001 ,
#960000000
0"
b11110110001 #
b11011101101 $
0'
b11110110001 )
b11011101101 *
#968000000
1"
b11010111110 %
b11010000101 &
1'
b11010111110 +
b11010000101 ,
#976000000
0"
b11110111100 #
b11011010111 $
0'
b11110111100 )
b11011010111 *
#984000000
1"
b00010110010 %
b11110101100 &
1'
b00010110010 +
b11110101100 ,
#992000000
0"
b11111000011 #
b11010111011 $
0'
b11111000011 )
b11010111011 *
#1000000000
1"
b01000110011 %
b00000010000 &
1'
b01000110011 +
b00000010000 ,
#1008000000
0"
b11111001010 #
b11010100000 $
0'
b11111001010 )
b11010100000 *
#1016000000
1"
b01101000001 %
b11110011101 &
1'
b01101000001 +
b11110011101 ,
#1024000000
0"
b11111010110 #
b11010010011 $
0'
b11111010110 )
b11010010011 *
#1032000000
1"
b01111110000 %
b11001111011 &
1'
b01111110000 +
b11001111011 ,
#1040000000
0"
b11111101010 #
b11010011100 $
0'
b11111101010 )
b11010011100 *
#1048000000
1"
b10001101101 %
b10011111010 &
1'
b10001101101 +
b10011111010 ,
#1056000000
0"
b00000000110 #
b11011000011 $
0'
b00000000110 )
b11011000011 *
#1064000000
1"
b10011101111 %
b01110100110 &
1'
b10011101111 +
b01110100110 ,
#1072000000
0"
b00000101100 #
b11100001101 $
0'
b00000101100 )
b11100001101 *
#1080000000
1"
b10110110010 %
b01100001011 &
1'
b10110110010 +
b01100001011 ,
#1088000000
0"
b00001011000 #
b11101110110 $
0'
b00001011000 )
b11101110110 *
#1096000000
1"
b11011011110 %
b01110111010 &
1'
b11011011110 +
b01110111010 ,
#1104000000
0"
b00010001000 #
b11111111010 $
0'
b00010001000 )
b11111111010 *
#1112000000
1"
b00010001100 %
b11000011100 &
1'
b00010001100 +
b11000011100 ,
#1120000000
0"
b00010110100 #
b00010001100 $
0'
b00010110100 )
b00010001100 *
#1128000000
1"
b01010110010 %
b01001011110 &
1'
b01010110010 +
b01001011110 ,
#1136000000
0"
b00011011001 #
b00100011110 $
0'
b00011011001 )
b00100011110 *
#1144000000
1"
b10100111100 %
b00001110001 &
1'
b10100111100 +
b00001110001 ,
#1152000000
0"
b00011101111 #
b00110011110 $
0'
b00011101111 )
b00110011110 *
#1160000000
1"
b11111100100 %
b11111101100 &
1'
b11111100100 +
b11111101100 ,
#1168000000
0"
b00011110011 #
b00111111100 $
0'
b00011110011 )
b00111111100 *
#1176000000
1"
b01001101001 %
b00000110100 &
1'
b01001101001 +
b00000110100 ,
#1184000000
0"
b00011100010 #
b01000101101 $
0'
b00011100010 )
b01000101101 *
#1192000000
1"
b10001101100 %
b00001101000 &
1'
b10001101100 +
b00001101000 ,
#1200000000
0"
b00010111100 #
b01000101000 $
0'
b00010111100 )
b01000101000 *
#1208000000
1"
b10110100111 %
b11110011000 &
1'
b10110100111 +
b11110011000 ,
#1216000000
0"
b00010000011 #
b00111101100 $
0'
b00010000011 )
b00111101100 *
#1224000000
1"
b10111010100 %
b10011100011 &
1'
b10111010100 +
b10011100011 ,
#1232000000
0"
b00000111011 #
b00101111111 $
0'
b00000111011 )
b00101111111 *
#1240000000
1"
b10011010101 %
b11110010101 &
1'
b10011010101 +
b11110010101 ,
#1248000000
0"
b11111101010 #
b00011101101 $
0'
b11111101010 )
b00011101101 *
#1256000000
1"
b01010100101 %
b11101000101 &
1'
b01010100101 +
b11101000101 ,
#1264000000
0"
b11110011000 #
b00001001000 $
0'
b11110011000 )
b00001001000 *
#1272000000
1"
b11101100010 %
b01111011111 &
1'
b11101100010 +
b01111011111 ,
#1280000000
0"
b11101001101 #
b11110100001 $
0'
b11101001101 )
b11110100001 *
#1288000000
1"
b01101001000 %
b10110111000 &
1'
b01101001000 +
b10110111000 ,
#1296000000
0"
b11100001110 #
b11100001110 $
0'
b11100001110 )
b11100001110 *
#1304000000
1"
b11010110001 %
b10110000100 &
1'
b11010110001 +
b10110000100 ,
#1312000000
0"
b11011100011 #
b11010011100 $
0'
b11011100011 )
b11010011100 *
#1320000000
1"
b01000001011 %
b10000101110 &
1'
b01000001011 +
b10000101110 ,
#1328000000
0"
b11011001111 #
b11001011000 $
0'
b11011001111 )
b11001011000 *
#1336000000
1"
b10110111111 %
b01011010011 &
1'
b10110111111 +
b01011010011 ,
#1344000000
0"
b11011010101 #
b11001000110 $
0'
b11011010101 )
b11001000110 *
#1352000000
1"
b01000110110 %
b01001110111 &
1'
b01000110110 +
b01001110111 ,
#1360000000
0"
b11011110101 #
b11001100011 $
0'
b11011110101 )
b11001100011 *
#1368000000
1"
b11111000000 %
b10000001010 &
1'
b11111000000 +
b10000001010 ,
#1376000000
0"
b11100101110 #
b11010100101 $
0'
b11100101110 )
b11010100101 *
#1384000000
1"
b11010100011 %
b00000100010 &
1'
b11010100011 +
b00000100010 ,
#1392000000
0"
b11101111101 #
b11011111110 $
0'
b11101111101 )
b11011111110 *
#1400000000
1"
b11011111101 %
b11100000101 &
1'
b11011111101 +
b11100000101 ,
#1408000000
0"
b11111011101 #
b11101011101 $
0'
b11111011101 )
b11101011101 *
#1416000000
1"
b00011011000 %
b00010000110 &
1'
b00011011000 +
b00010000110 ,
#1424000000
0"
b00001001001 #
b11110110010 $
0'
b00001001001 )
b11110110010 *
#1432000000
1"
b10000100000 %
b10000011110 &
1'
b10000100000 +
b10000011110 ,
#1440000000
0"
b00010111001 #
b11111101110 $
0'
b00010111001 )
b11111101110 *
#1448000000
1"
b00010101000 %
b00100000000 &
1'
b00010101000 +
b00100000000 ,
#1456000000
0"
b00100100111 #
b00000000111 $
0'
b00100100111 )
b00000000111 *
#1464000000
1"
b11000101111 %
b11001000001 &
1'
b11000101111 +
b11001000001 ,
#1472000000
0"
b00110001011 #
b11111111010 $
0'
b00110001011 )
b11111111010 *
#1480000000
1"
b10001011011 %
b01011110001 &
1'
b10001011011 +
b01011110001 ,
#1488000000
0"
b00111100000 #
b11111001001 $
0'
b00111100000 )
b11111001001 *
#1496000000
1"
b01011001101 %
b11001000011 &
1'
b01011001101 +
b11001000011 ,
#1504000000
0"
b01000011110 #
b11101111101 $
0'
b01000011110 )
b11101111101 *
#1512000000
1"
b00100010111 %
b11110101011 &
1'
b00100010111 +
b11110101011 ,
#1520000000
0"
b01001000001 #
b11100100010 $
0'
b01001000001 )
b11100100010 *
#1528000000
1"
b11011011010 %
b11011110010 &
1'
b11011011010 +
b11011110010 ,
#1536000000
0"
b01001000100 #
b11011000110 $
0'
b01001000100 )
b11011000110 *
#1544000000
1"
b01110101101 %
b10001000000 &
1'
b01110101101 +
b10001000000 ,
#1552000000
0"
b01000100110 #
b11001111000 $
0'
b01000100110 )
b11001111000 *
#1560000000
1"
b11100111011 %
b00000001000 &
1'
b11100111011 +
b00000001000 ,
#1568000000
0"
b00111100111 #
b11001000010 $
0'
b00111100111 )
b11001000010 *
#1576000000
1"
b00100101111 %
b01011111001 &
1'
b00100101111 +
b01011111001 ,
#1584000000
0"
b00110001010 #
b11000101101 $
0'
b00110001010 )
b11000101101 *
#1592000000
1"
b00101010111 %
b10111100000 &
1'
b00101010111 +
b10111100000 ,
#1600000000
0"
b00100010110 #
b11000111011 $
0'
b00100010110 )
b11000111011 *
#1608000000
1"
b11110010101 %
b00110000000 &
1'
b11110010101 +
b00110000000 ,
#1616000000
0"
b00010010010 #
b11001101001 $
0'
b00010010010 )
b11001101001 *
#1624000000
1"
b01111110011 %
b11010000011 &
1'
b01111110011 +
b11010000011 ,
#1632000000
0"
b00000001000 #
b11010110000 $
0'
b00000001000 )
b11010110000 *
#1640000000
1"
b11010100011 %
b10101010010 &
1'
b11010100011 +
b10101010010 ,
#1648000000
0"
b11110000100 #
b11100000111 $
0'
b11110000100 )
b11100000111 *
#1656000000
1"
b11111111010 %
b11000010101 &
1'
b11111111010 +
b11000010101 ,
#1664000000
0"
b11100010000 #
b11101100010 $
0'
b11100010000 )
b11101100010 *
#1672000000
1"
b00001110000 %
b00010100100 &
1'
b00001110000 +
b00010100100 ,
#1680000000
0"
b11010110111 #
b11110110101 $
0'
b11010110111 )
b11110110101 *
#1688000000
1"
b00010010110 %
b10010100000 &
1'
b00010010110 +
b10010100000 ,
#1696000000
0"
b11010000000 #
b11111110110 $
0'
b11010000000 )
b11111110110 *
#1704000000
1"
b00100001100 %
b00101111101 &
1'
b00100001100 +
b00101111101 ,
#1712000000
0"
b11001110000 #
b00000100001 $
0'
b11001110000 )
b00000100001 *
#1720000000
1"
b01001110111 %
b11010010110 &
1'
b01001110111 +
b11010010110 ,
#1728000000
0"
b11010000111 #
b00000110000 $
0'
b11010000111 )
b00000110000 *
#1736000000
1"
b10101100011 %
b01101000001 &
1'
b10101100011 +
b01101000001 ,
#1744000000
0"
b11011000011 #
b00000100101 $
0'
b11011000011 )
b00000100101 *
#1752000000
1"
b01001000011 %
b11011111100 &
1'
b01001000011 +
b11011111100 ,
#1760000000
0"
b11100011100 #
b00000000010 $
0'
b11100011100 )
b00000000010 *
#1768000000
1"
b00101010011 %
b00101100011 &
1'
b00101010011 +
b00101100011 ,
#1776000000
0"
b11110001001 #
b11111001100 $
0'
b11110001001 )
b11111001100 *
#1784000000
1"
b01010100010 %
b01001001110 &
1'
b01010100010 +
b01001001110 ,
#1792000000
0"
b00000000000 #
b11110001001 $
0'
b00000000000 )
b11110001001 *
#1800000000
1"
b10111111110 %
b00110110011 &
1'
b10111111110 +
b00110110011 ,
#1808000000
0"
b00001110100 #
b11101000000 $
0'
b00001110100 )
b11101000000 *
#1816000000
1"
b01100001000 %
b11110111111 &
1'
b01100001000 +
b11110111111 ,
#1824000000
0"
b00011011001 #
b11011110111 $
0'
b00011011001 )
b11011110111 *
#1832000000
1"
b00100111001 %
b10010110011 &
1'
b00100111001 +
b10010110011 ,
#1840000000
0"
b00100101001 #
b11010110010 $
0'
b00100101001 )
b11010110010 *
#1848000000
1"
b11111110001 %
b00011101001 &
1'
b11111110001 +
b00011101001 ,
