VHDL/DPD.vhd
LIBRARY IEEE;
USE IEEE.STD_LOGIC_1164.ALL;
USE IEEE.NUMERIC_STD.ALL;
USE work.functions.ALL;

ENTITY DPD IS
    PORT (
        clk    : IN  STD_LOGIC;
        reset  : IN  STD_LOGIC;
        UR     : IN  STD_LOGIC_VECTOR(n_bits_resolution-1 DOWNTO 0);
        UI     : IN  STD_LOGIC_VECTOR(n_bits_resolution-1 DOWNTO 0);
        UR_out : OUT STD_LOGIC_VECTOR(n_bits_resolution-1 DOWNTO 0);
        UI_out : OUT STD_LOGIC_VECTOR(n_bits_resolution-1 DOWNTO 0)
    );
END ENTITY;

ARCHITECTURE rtl OF DPD IS

    --------------------------------------------------------------------
    -- Sinais principais
    --------------------------------------------------------------------
    SIGNAL delay_line      : delay_line_t   := (OTHERS => zero_complex);

    SIGNAL XX              : power_vector_t := (OTHERS => zero_complex);
    SIGNAL multiplied      : power_vector_t := (OTHERS => zero_complex);
    SIGNAL multiplied_next : power_vector_t := (OTHERS => zero_complex);

    --------------------------------------------------------------------
    -- Estágio base/msq
    --------------------------------------------------------------------
    SIGNAL base_vec      : delay_line_t := (OTHERS => zero_complex);
    SIGNAL msq_vec       : mag_array_t  := (OTHERS => 0);
    SIGNAL base_vec_next : delay_line_t := (OTHERS => zero_complex);
    SIGNAL msq_vec_next  : mag_array_t  := (OTHERS => 0);

    --------------------------------------------------------------------
    -- Pipeline por ordem
    --------------------------------------------------------------------
    SIGNAL term_pipe      : term_pipe_local_t := (OTHERS => (OTHERS => zero_complex));
    SIGNAL msq_pipe       : mag_pipe_local_t  := (OTHERS => (OTHERS => 0));
    SIGNAL term_pipe_next : term_pipe_local_t := (OTHERS => (OTHERS => zero_complex));
    SIGNAL msq_pipe_next  : mag_pipe_local_t  := (OTHERS => (OTHERS => 0));

    --------------------------------------------------------------------
    -- Alinhamento temporal das ordens
    --------------------------------------------------------------------
    SIGNAL align_pipe      : align_pipe_local_t := (OTHERS => (OTHERS => (OTHERS => zero_complex)));
    SIGNAL align_pipe_next : align_pipe_local_t := (OTHERS => (OTHERS => (OTHERS => zero_complex)));

    --------------------------------------------------------------------
    -- Árvore de soma
    --------------------------------------------------------------------
    SIGNAL sum_tree : sum_tree_t := (OTHERS => (OTHERS => zero_acc_complex));

BEGIN

    --------------------------------------------------------------------
    -- 1. Delay line
    --------------------------------------------------------------------
    delay_process : PROCESS(clk)
        VARIABLE din        : complex_number;
        VARIABLE temp_delay : delay_line_t;
    BEGIN
        IF rising_edge(clk) THEN
            IF reset = '1' THEN
                delay_line <= (OTHERS => zero_complex);
            ELSE
                din.reall := clip_data(to_integer(signed(UR)));
                din.imag  := clip_data(to_integer(signed(UI)));

                temp_delay := delay_line;
                temp_delay(0) := din;

                FOR m IN 1 TO n_signals_used - 1 LOOP
                    temp_delay(m) := delay_line(m - 1);
                END LOOP;

                delay_line <= temp_delay;
            END IF;
        END IF;
    END PROCESS;

    --------------------------------------------------------------------
    -- 2. Geração combinacional paralela de base_vec_next e msq_vec_next
    --------------------------------------------------------------------
    gen_prep_power : FOR m IN 0 TO n_signals_used - 1 GENERATE
    BEGIN
        base_vec_next(m).reall <= clip_data(delay_line(m).reall);
        base_vec_next(m).imag  <= clip_data(delay_line(m).imag);

        msq_vec_next(m) <=
            readeq(clip_data(delay_line(m).reall) * clip_data(delay_line(m).reall)) +
            readeq(clip_data(delay_line(m).imag)  * clip_data(delay_line(m).imag));
    END GENERATE;

    --------------------------------------------------------------------
    -- 2b. Registro de base_vec e msq_vec
    --------------------------------------------------------------------
    prep_power_process : PROCESS(clk)
    BEGIN
        IF rising_edge(clk) THEN
            IF reset = '1' THEN
                base_vec <= (OTHERS => zero_complex);
                msq_vec  <= (OTHERS => 0);
            ELSE
                base_vec <= base_vec_next;
                msq_vec  <= msq_vec_next;
            END IF;
        END IF;
    END PROCESS;

    --------------------------------------------------------------------
    -- 3. Pipeline por ordem
    --------------------------------------------------------------------
    gen_term_stage0 : FOR m IN 0 TO n_signals_used - 1 GENERATE
    BEGIN
        term_pipe_next(0, m) <= base_vec(m);
        msq_pipe_next(0, m)  <= msq_vec(m);
    END GENERATE;

    gen_term_stages : FOR s IN 1 TO max_poly_degree - 1 GENERATE
        gen_term_delay : FOR m IN 0 TO n_signals_used - 1 GENERATE
        BEGIN
            term_pipe_next(s, m).reall <= clip_data(
                readeq(term_pipe(s - 1, m).reall * msq_pipe(s - 1, m))
            );

            term_pipe_next(s, m).imag <= clip_data(
                readeq(term_pipe(s - 1, m).imag * msq_pipe(s - 1, m))
            );

            msq_pipe_next(s, m) <= msq_pipe(s - 1, m);
        END GENERATE;
    END GENERATE;

    terms_pipe_process : PROCESS(clk)
    BEGIN
        IF rising_edge(clk) THEN
            IF reset = '1' THEN
                term_pipe <= (OTHERS => (OTHERS => zero_complex));
                msq_pipe  <= (OTHERS => (OTHERS => 0));
            ELSE
                term_pipe <= term_pipe_next;
                msq_pipe  <= msq_pipe_next;
            END IF;
        END IF;
    END PROCESS;

    --------------------------------------------------------------------
    -- 4. Alinhamento temporal das ordens
    --------------------------------------------------------------------
    gen_align_in : FOR p IN 0 TO max_poly_degree - 1 GENERATE
        gen_align_in_delay : FOR m IN 0 TO n_signals_used - 1 GENERATE
        BEGIN
            align_pipe_next(0, p, m) <= term_pipe(p, m);
        END GENERATE;
    END GENERATE;

    gen_align_shift : FOR d IN 1 TO max_poly_degree - 1 GENERATE
        gen_align_order : FOR p IN 0 TO max_poly_degree - 1 GENERATE
            gen_align_delay : FOR m IN 0 TO n_signals_used - 1 GENERATE
            BEGIN
                align_pipe_next(d, p, m) <= align_pipe(d - 1, p, m);
            END GENERATE;
        END GENERATE;
    END GENERATE;

    align_process : PROCESS(clk)
    BEGIN
        IF rising_edge(clk) THEN
            IF reset = '1' THEN
                align_pipe <= (OTHERS => (OTHERS => (OTHERS => zero_complex)));
            ELSE
                align_pipe <= align_pipe_next;
            END IF;
        END IF;
    END PROCESS;

    --------------------------------------------------------------------
    -- 5. Empacotamento linear dos termos alinhados em XX
    --------------------------------------------------------------------
    pack_xx_process : PROCESS(clk)
        VARIABLE temp_xx : power_vector_t;
        VARIABLE idx     : INTEGER;
        VARIABLE dsel    : INTEGER;
    BEGIN
        IF rising_edge(clk) THEN
            IF reset = '1' THEN
                XX <= (OTHERS => zero_complex);
            ELSE
                temp_xx := (OTHERS => zero_complex);
                idx := 0;

                FOR m IN 0 TO n_signals_used - 1 LOOP
                    FOR p IN 0 TO poly_degree_per_delay(m) - 1 LOOP
                        dsel := max_poly_degree - 1 - p;
                        temp_xx(idx) := align_pipe(dsel, p, m);
                        idx := idx + 1;
                    END LOOP;
                END LOOP;

                XX <= temp_xx;
            END IF;
        END IF;
    END PROCESS;

    --------------------------------------------------------------------
    -- 6. Multiplicação paralela pelos coeficientes
    --------------------------------------------------------------------
    gen_mult : FOR k IN 0 TO n_total_terms - 1 GENERATE
    BEGIN
        multiplied_next(k) <= cmul(coefficients(k), XX(k));
    END GENERATE;

    mult_process : PROCESS(clk)
    BEGIN
        IF rising_edge(clk) THEN
            IF reset = '1' THEN
                multiplied <= (OTHERS => zero_complex);
            ELSE
                multiplied <= multiplied_next;
            END IF;
        END IF;
    END PROCESS;

    --------------------------------------------------------------------
    -- 7. Árvore de soma combinacional
    --------------------------------------------------------------------
    gen_sum_input : FOR k IN 0 TO n_total_terms - 1 GENERATE
    BEGIN
        sum_tree(0, k).reall <= multiplied(k).reall;
        sum_tree(0, k).imag  <= multiplied(k).imag;
    END GENERATE;

    gen_sum_levels : FOR level IN 1 TO SUM_LEVELS GENERATE
        gen_sum_nodes : FOR k IN 0 TO n_total_terms - 1 GENERATE
        BEGIN
            valid_pair : IF (2 * k + 1) < level_size(level - 1) GENERATE
            BEGIN
                sum_tree(level, k).reall <=
                    sum_tree(level - 1, 2 * k).reall +
                    sum_tree(level - 1, 2 * k + 1).reall;

                sum_tree(level, k).imag <=
                    sum_tree(level - 1, 2 * k).imag +
                    sum_tree(level - 1, 2 * k + 1).imag;
            END GENERATE;

            valid_single : IF ((2 * k) < level_size(level - 1)) AND
                              ((2 * k + 1) >= level_size(level - 1)) GENERATE
            BEGIN
                sum_tree(level, k) <= sum_tree(level - 1, 2 * k);
            END GENERATE;

            invalid_node : IF (2 * k) >= level_size(level - 1) GENERATE
            BEGIN
                sum_tree(level, k) <= zero_acc_complex;
            END GENERATE;
        END GENERATE;
    END GENERATE;

    --------------------------------------------------------------------
    -- 8. Registro da soma final
    --------------------------------------------------------------------
    sum_process : PROCESS(clk)
        VARIABLE acc_re, acc_im : INTEGER;
    BEGIN
        IF rising_edge(clk) THEN
            IF reset = '1' THEN
                UR_out <= (OTHERS => '0');
                UI_out <= (OTHERS => '0');
            ELSE
                acc_re := sum_tree(SUM_LEVELS, 0).reall;
                acc_im := sum_tree(SUM_LEVELS, 0).imag;

                UR_out <= STD_LOGIC_VECTOR(to_signed(clip_data(acc_re), n_bits_resolution));
                UI_out <= STD_LOGIC_VECTOR(to_signed(clip_data(acc_im), n_bits_resolution));
            END IF;
        END IF;
    END PROCESS;

END ARCHITECTURE;

tb_main.vhd
--------------------------------------------------------------------------------
LIBRARY ieee;
USE ieee.std_logic_1164.ALL;
  
ENTITY tb IS
END tb;
 
ARCHITECTURE behavior OF tb IS 
    CONSTANT n_bits_resolution : INTEGER := 9;
    CONSTANT n_bits_overflow : INTEGER := 8;
    CONSTANT n_signals_used : INTEGER := 2;
    CONSTANT n_polygnos_degree : INTEGER := 2;
    -- Component Declaration for the Unit Under Test (UUT)
    COMPONENT dpd
        PORT (
            reset : IN STD_LOGIC;
            clk : IN STD_LOGIC;
            UR : IN STD_LOGIC_VECTOR(n_bits_resolution - 1 DOWNTO 0);
            UI : IN STD_LOGIC_VECTOR(n_bits_resolution - 1 DOWNTO 0);
            UR_out : OUT STD_LOGIC_VECTOR(n_bits_resolution - 1 DOWNTO 0);
            UI_out : OUT STD_LOGIC_VECTOR(n_bits_resolution - 1 DOWNTO 0)
        );
    END COMPONENT;

    -- Signals for connecting to UUT
    SIGNAL reset : STD_LOGIC := '0';
    SIGNAL clk : STD_LOGIC := '0';
    SIGNAL UR : STD_LOGIC_VECTOR(n_bits_resolution - 1 DOWNTO 0) := (OTHERS => '0');
    SIGNAL UI : STD_LOGIC_VECTOR(n_bits_resolution - 1 DOWNTO 0) := (OTHERS => '0');
    SIGNAL UR_out : STD_LOGIC_VECTOR(n_bits_resolution - 1 DOWNTO 0) := (OTHERS => '0');
    SIGNAL UI_out : STD_LOGIC_VECTOR(n_bits_resolution - 1 DOWNTO 0);

    -- Clock period definition
    CONSTANT clk_period : TIME := 10 ns;
 
BEGIN
 
	-- Instantiate the Unit Under Test (UUT)
   uut: DPD PORT MAP (
          reset => reset,
          clk => clk,
          UR => UR,
          UI => UI,
          UR_out => UR_out,
          UI_out => UI_out
        );

   -- Clock process definitions
   clk_process :process
   begin
		clk <= '0';
		wait for clk_period/2;
		clk <= '1';
		wait for clk_period/2;
   end process;
 

   -- Stimulus process
   stim_proc: process
   begin		
      -- hold reset state for 100 ns.
      wait for 100 ns;	

      wait for clk_period*10;

      -- insert stimulus here 
      wait;
   end process;

      -- in process
   calc_proc: process
   begin		
      reset <= '1';
      wait for 2 * clk_period;	
      reset <= '0';
      WAIT FOR clk_period;
      
UR <= "000111101";
UI <= "010100000";
WAIT FOR clk_period;
UR <= "000011100";
UI <= "010100101";
WAIT FOR clk_period;
UR <= "111111001";
UI <= "010100001";
WAIT FOR clk_period;
UR <= "111011010";
UI <= "010010111";
WAIT FOR clk_period;
UR <= "110111101";
UI <= "010001000";
WAIT FOR clk_period;
UR <= "110100101";
UI <= "001110100";
WAIT FOR clk_period;
UR <= "110001111";
UI <= "001011110";
WAIT FOR clk_period;
UR <= "101111110";
UI <= "001001000";
WAIT FOR clk_period;
UR <= "101110000";
UI <= "000110101";
WAIT FOR clk_period;
UR <= "101100110";
UI <= "000100100";
WAIT FOR clk_period;
UR <= "101011111";
UI <= "000011010";
WAIT FOR clk_period;
UR <= "101011011";
UI <= "000010101";
WAIT FOR clk_period;
UR <= "101011010";
UI <= "000010111";
WAIT FOR clk_period;
UR <= "101011011";
UI <= "000011100";
WAIT FOR clk_period;
UR <= "101011100";
UI <= "000100110";
WAIT FOR clk_period;
UR <= "101011110";
UI <= "000101111";
WAIT FOR clk_period;
UR <= "101100000";
UI <= "000111001";
WAIT FOR clk_period;
UR <= "101100010";
UI <= "000111110";
WAIT FOR clk_period;
UR <= "101100001";
UI <= "000111111";
WAIT FOR clk_period;
UR <= "101011111";
UI <= "000111011";
WAIT FOR clk_period;
UR <= "101011010";
UI <= "000110010";
WAIT FOR clk_period;
UR <= "101010100";
UI <= "000100101";
WAIT FOR clk_period;
UR <= "101010000";
UI <= "000010110";
WAIT FOR clk_period;
UR <= "101001011";
UI <= "000001011";
WAIT FOR clk_period;
UR <= "101000111";
UI <= "000000011";
WAIT FOR clk_period;
UR <= "101001001";
UI <= "000000001";
WAIT FOR clk_period;
UR <= "101001111";
UI <= "000001000";
WAIT FOR clk_period;
UR <= "101011011";
UI <= "000011000";
WAIT FOR clk_period;
UR <= "101101101";
UI <= "000110001";
WAIT FOR clk_period;
UR <= "110000011";
UI <= "001010000";
WAIT FOR clk_period;
UR <= "110011110";
UI <= "001110010";
WAIT FOR clk_period;
UR <= "110111101";
UI <= "010010011";
WAIT FOR clk_period;
UR <= "111011011";
UI <= "010110001";
WAIT FOR clk_period;
UR <= "111111000";
UI <= "011000101";
WAIT FOR clk_period;
UR <= "000010011";
UI <= "011001011";
WAIT FOR clk_period;
UR <= "000101000";
UI <= "011000011";
WAIT FOR clk_period;
UR <= "000111000";
UI <= "010101100";
WAIT FOR clk_period;
UR <= "001000000";
UI <= "010000111";
WAIT FOR clk_period;
UR <= "001000001";
UI <= "001010101";
WAIT FOR clk_period;
UR <= "000111100";
UI <= "000011110";
WAIT FOR clk_period;
UR <= "000101111";
UI <= "111100100";
WAIT FOR clk_period;
UR <= "000011100";
UI <= "110101101";
WAIT FOR clk_period;
UR <= "000000110";
UI <= "110000000";
WAIT FOR clk_period;
UR <= "111101111";
UI <= "101011100";
WAIT FOR clk_period;
UR <= "111010110";
UI <= "101001010";
WAIT FOR clk_period;
UR <= "110111100";
UI <= "101001001";
WAIT FOR clk_period;
UR <= "110100011";
UI <= "101010101";
WAIT FOR clk_period;
UR <= "110001111";
UI <= "101110001";
WAIT FOR clk_period;
UR <= "101111101";
UI <= "110010110";
WAIT FOR clk_period;
UR <= "101101101";
UI <= "111000001";
WAIT FOR clk_period;

      -- insert stimulus here 
      wait;
   end process;
    
END;

VHDL/output.vcd
$date
  Wed Apr 29 17:53:36 2026
$end
$version
  GHDL v0
$end
$timescale
  1 fs
$end
$scope module standard $end
$upscope $end
$scope module textio $end
$upscope $end
$scope module std_logic_1164 $end
$upscope $end
$scope module numeric_std $end
$upscope $end
$scope module std_logic_textio $end
$upscope $end
$scope module env $end
$upscope $end
$scope module functions $end
$upscope $end
$scope module tb $end
$var reg 1 ! reset $end
$var reg 1 " clk $end
$var reg 11 # ur[10:0] $end
$var reg 11 $ ui[10:0] $end
$var reg 11 % ur_out[10:0] $end
$var reg 11 & ui_out[10:0] $end
$scope module uut $end
$var reg 1 ' clk $end
$var reg 1 ( reset $end
$var reg 11 ) ur[10:0] $end
$var reg 11 * ui[10:0] $end
$var reg 11 + ur_out[10:0] $end
$var reg 11 , ui_out[10:0] $end
$comment delay_line is not handled $end
$comment xx is not handled $end
$comment multiplied is not handled $end
$comment multiplied_next is not handled $end
$comment base_vec is not handled $end
$comment msq_vec is not handled $end
$comment base_vec_next is not handled $end
$comment msq_vec_next is not handled $end
$comment term_pipe is not handled $end
$comment msq_pipe is not handled $end
$comment term_pipe_next is not handled $end
$comment msq_pipe_next is not handled $end
$comment align_pipe is not handled $end
$comment align_pipe_next is not handled $end
$comment sum_tree is not handled $end
$scope module gen_prep_power(0) $end
$upscope $end
$scope module gen_prep_power(1) $end
$upscope $end
$scope module gen_prep_power(2) $end
$upscope $end
$scope module gen_term_stage0(0) $end
$upscope $end
$scope module gen_term_stage0(1) $end
$upscope $end
$scope module gen_term_stage0(2) $end
$upscope $end
$scope module gen_term_stages(1) $end
$scope module gen_term_delay(0) $end
$upscope $end
$scope module gen_term_delay(1) $end
$upscope $end
$scope module gen_term_delay(2) $end
$upscope $end
$upscope $end
$scope module gen_term_stages(2) $end
$scope module gen_term_delay(0) $end
$upscope $end
$scope module gen_term_delay(1) $end
$upscope $end
$scope module gen_term_delay(2) $end
$upscope $end
$upscope $end
$scope module gen_term_stages(3) $end
$scope module gen_term_delay(0) $end
$upscope $end
$scope module gen_term_delay(1) $end
$upscope $end
$scope module gen_term_delay(2) $end
$upscope $end
$upscope $end
$scope module gen_term_stages(4) $end
$scope module gen_term_delay(0) $end
$upscope $end
$scope module gen_term_delay(1) $end
$upscope $end
$scope module gen_term_delay(2) $end
$upscope $end
$upscope $end
$scope module gen_align_in(0) $end
$scope module gen_align_in_delay(0) $end
$upscope $end
$scope module gen_align_in_delay(1) $end
$upscope $end
$scope module gen_align_in_delay(2) $end
$upscope $end
$upscope $end
$scope module gen_align_in(1) $end
$scope module gen_align_in_delay(0) $end
$upscope $end
$scope module gen_align_in_delay(1) $end
$upscope $end
$scope module gen_align_in_delay(2) $end
$upscope $end
$upscope $end
$scope module gen_align_in(2) $end
$scope module gen_align_in_delay(0) $end
$upscope $end
$scope module gen_align_in_delay(1) $end
$upscope $end
$scope module gen_align_in_delay(2) $end
$upscope $end
$upscope $end
$scope module gen_align_in(3) $end
$scope module gen_align_in_delay(0) $end
$upscope $end
$scope module gen_align_in_delay(1) $end
$upscope $end
$scope module gen_align_in_delay(2) $end
$upscope $end
$upscope $end
$scope module gen_align_in(4) $end
$scope module gen_align_in_delay(0) $end
$upscope $end
$scope module gen_align_in_delay(1) $end
$upscope $end
$scope module gen_align_in_delay(2) $end
$upscope $end
$upscope $end
$scope module gen_align_shift(1) $end
$scope module gen_align_order(0) $end
$scope module gen_align_delay(0) $end
$upscope $end
$scope module gen_align_delay(1) $end
$upscope $end
$scope module gen_align_delay(2) $end
$upscope $end
$upscope $end
$scope module gen_align_order(1) $end
$scope module gen_align_delay(0) $end
$upscope $end
$scope module gen_align_delay(1) $end
$upscope $end
$scope module gen_align_delay(2) $end
$upscope $end
$upscope $end
$scope module gen_align_order(2) $end
$scope module gen_align_delay(0) $end
$upscope $end
$scope module gen_align_delay(1) $end
$upscope $end
$scope module gen_align_delay(2) $end
$upscope $end
$upscope $end
$scope module gen_align_order(3) $end
$scope module gen_align_delay(0) $end
$upscope $end
$scope module gen_align_delay(1) $end
$upscope $end
$scope module gen_align_delay(2) $end
$upscope $end
$upscope $end
$scope module gen_align_order(4) $end
$scope module gen_align_delay(0) $end
$upscope $end
$scope module gen_align_delay(1) $end
$upscope $end
$scope module gen_align_delay(2) $end
$upscope $end
$upscope $end
$upscope $end
$scope module gen_align_shift(2) $end
$scope module gen_align_order(0) $end
$scope module gen_align_delay(0) $end
$upscope $end
$scope module gen_align_delay(1) $end
$upscope $end
$scope module gen_align_delay(2) $end
$upscope $end
$upscope $end
$scope module gen_align_order(1) $end
$scope module gen_align_delay(0) $end
$upscope $end
$scope module gen_align_delay(1) $end
$upscope $end
$scope module gen_align_delay(2) $end
$upscope $end
$upscope $end
$scope module gen_align_order(2) $end
$scope module gen_align_delay(0) $end
$upscope $end
$scope module gen_align_delay(1) $end
$upscope $end
$scope module gen_align_delay(2) $end
$upscope $end
$upscope $end
$scope module gen_align_order(3) $end
$scope module gen_align_delay(0) $end
$upscope $end
$scope module gen_align_delay(1) $end
$upscope $end
$scope module gen_align_delay(2) $end
$upscope $end
$upscope $end
$scope module gen_align_order(4) $end
$scope module gen_align_delay(0) $end
$upscope $end
$scope module gen_align_delay(1) $end
$upscope $end
$scope module gen_align_delay(2) $end
$upscope $end
$upscope $end
$upscope $end
$scope module gen_align_shift(3) $end
$scope module gen_align_order(0) $end
$scope module gen_align_delay(0) $end
$upscope $end
$scope module gen_align_delay(1) $end
$upscope $end
$scope module gen_align_delay(2) $end
$upscope $end
$upscope $end
$scope module gen_align_order(1) $end
$scope module gen_align_delay(0) $end
$upscope $end
$scope module gen_align_delay(1) $end
$upscope $end
$scope module gen_align_delay(2) $end
$upscope $end
$upscope $end
$scope module gen_align_order(2) $end
$scope module gen_align_delay(0) $end
$upscope $end
$scope module gen_align_delay(1) $end
$upscope $end
$scope module gen_align_delay(2) $end
$upscope $end
$upscope $end
$scope module gen_align_order(3) $end
$scope module gen_align_delay(0) $end
$upscope $end
$scope module gen_align_delay(1) $end
$upscope $end
$scope module gen_align_delay(2) $end
$upscope $end
$upscope $end
$scope module gen_align_order(4) $end
$scope module gen_align_delay(0) $end
$upscope $end
$scope module gen_align_delay(1) $end
$upscope $end
$scope module gen_align_delay(2) $end
$upscope $end
$upscope $end
$upscope $end
$scope module gen_align_shift(4) $end
$scope module gen_align_order(0) $end
$scope module gen_align_delay(0) $end
$upscope $end
$scope module gen_align_delay(1) $end
$upscope $end
$scope module gen_align_delay(2) $end
$upscope $end
$upscope $end
$scope module gen_align_order(1) $end
$scope module gen_align_delay(0) $end
$upscope $end
$scope module gen_align_delay(1) $end
$upscope $end
$scope module gen_align_delay(2) $end
$upscope $end
$upscope $end
$scope module gen_align_order(2) $end
$scope module gen_align_delay(0) $end
$upscope $end
$scope module gen_align_delay(1) $end
$upscope $end
$scope module gen_align_delay(2) $end
$upscope $end
$upscope $end
$scope module gen_align_order(3) $end
$scope module gen_align_delay(0) $end
$upscope $end
$scope module gen_align_delay(1) $end
$upscope $end
$scope module gen_align_delay(2) $end
$upscope $end
$upscope $end
$scope module gen_align_order(4) $end
$scope module gen_align_delay(0) $end
$upscope $end
$scope module gen_align_delay(1) $end
$upscope $end
$scope module gen_align_delay(2) $end
$upscope $end
$upscope $end
$upscope $end
$scope module gen_mult(0) $end
$upscope $end
$scope module gen_mult(1) $end
$upscope $end
$scope module gen_mult(2) $end
$upscope $end
$scope module gen_mult(3) $end
$upscope $end
$scope module gen_mult(4) $end
$upscope $end
$scope module gen_mult(5) $end
$upscope $end
$scope module gen_mult(6) $end
$upscope $end
$scope module gen_mult(7) $end
$upscope $end
$scope module gen_mult(8) $end
$upscope $end
$scope module gen_sum_input(0) $end
$upscope $end
$scope module gen_sum_input(1) $end
$upscope $end
$scope module gen_sum_input(2) $end
$upscope $end
$scope module gen_sum_input(3) $end
$upscope $end
$scope module gen_sum_input(4) $end
$upscope $end
$scope module gen_sum_input(5) $end
$upscope $end
$scope module gen_sum_input(6) $end
$upscope $end
$scope module gen_sum_input(7) $end
$upscope $end
$scope module gen_sum_input(8) $end
$upscope $end
$scope module gen_sum_levels(1) $end
$scope module gen_sum_nodes(0) $end
$scope module valid_pair $end
$upscope $end
$upscope $end
$scope module gen_sum_nodes(1) $end
$scope module valid_pair $end
$upscope $end
$upscope $end
$scope module gen_sum_nodes(2) $end
$scope module valid_pair $end
$upscope $end
$upscope $end
$scope module gen_sum_nodes(3) $end
$scope module valid_pair $end
$upscope $end
$upscope $end
$scope module gen_sum_nodes(4) $end
$scope module valid_single $end
$upscope $end
$upscope $end
$scope module gen_sum_nodes(5) $end
$scope module invalid_node $end
$upscope $end
$upscope $end
$scope module gen_sum_nodes(6) $end
$scope module invalid_node $end
$upscope $end
$upscope $end
$scope module gen_sum_nodes(7) $end
$scope module invalid_node $end
$upscope $end
$upscope $end
$scope module gen_sum_nodes(8) $end
$scope module invalid_node $end
$upscope $end
$upscope $end
$upscope $end
$scope module gen_sum_levels(2) $end
$scope module gen_sum_nodes(0) $end
$scope module valid_pair $end
$upscope $end
$upscope $end
$scope module gen_sum_nodes(1) $end
$scope module valid_pair $end
$upscope $end
$upscope $end
$scope module gen_sum_nodes(2) $end
$scope module valid_single $end
$upscope $end
$upscope $end
$scope module gen_sum_nodes(3) $end
$scope module invalid_node $end
$upscope $end
$upscope $end
$scope module gen_sum_nodes(4) $end
$scope module invalid_node $end
$upscope $end
$upscope $end
$scope module gen_sum_nodes(5) $end
$scope module invalid_node $end
$upscope $end
$upscope $end
$scope module gen_sum_nodes(6) $end
$scope module invalid_node $end
$upscope $end
$upscope $end
$scope module gen_sum_nodes(7) $end
$scope module invalid_node $end
$upscope $end
$upscope $end
$scope module gen_sum_nodes(8) $end
$scope module invalid_node $end
$upscope $end
$upscope $end
$upscope $end
$scope module gen_sum_levels(3) $end
$scope module gen_sum_nodes(0) $end
$scope module valid_pair $end
$upscope $end
$upscope $end
$scope module gen_sum_nodes(1) $end
$scope module valid_single $end
$upscope $end
$upscope $end
$scope module gen_sum_nodes(2) $end
$scope module invalid_node $end
$upscope $end
$upscope $end
$scope module gen_sum_nodes(3) $end
$scope module invalid_node $end
$upscope $end
$upscope $end
$scope module gen_sum_nodes(4) $end
$scope module invalid_node $end
$upscope $end
$upscope $end
$scope module gen_sum_nodes(5) $end
$scope module invalid_node $end
$upscope $end
$upscope $end
$scope module gen_sum_nodes(6) $end
$scope module invalid_node $end
$upscope $end
$upscope $end
$scope module gen_sum_nodes(7) $end
$scope module invalid_node $end
$upscope $end
$upscope $end
$scope module gen_sum_nodes(8) $end
$scope module invalid_node $end
$upscope $end
$upscope $end
$upscope $end
$scope module gen_sum_levels(4) $end
$scope module gen_sum_nodes(0) $end
$scope module valid_pair $end
$upscope $end
$upscope $end
$scope module gen_sum_nodes(1) $end
$scope module invalid_node $end
$upscope $end
$upscope $end
$scope module gen_sum_nodes(2) $end
$scope module invalid_node $end
$upscope $end
$upscope $end
$scope module gen_sum_nodes(3) $end
$scope module invalid_node $end
$upscope $end
$upscope $end
$scope module gen_sum_nodes(4) $end
$scope module invalid_node $end
$upscope $end
$upscope $end
$scope module gen_sum_nodes(5) $end
$scope module invalid_node $end
$upscope $end
$upscope $end
$scope module gen_sum_nodes(6) $end
$scope module invalid_node $end
$upscope $end
$upscope $end
$scope module gen_sum_nodes(7) $end
$scope module invalid_node $end
$upscope $end
$upscope $end
$scope module gen_sum_nodes(8) $end
$scope module invalid_node $end
$upscope $end
$upscope $end
$upscope $end
$upscope $end
$upscope $end
$enddefinitions $end
#0
1!
0"
b00000000000 #
b00000000000 $
bUUUUUUUUUUU %
bUUUUUUUUUUU &
0'
1(
b00000000000 )
b00000000000 *
bUUUUUUUUUUU +
bUUUUUUUUUUU ,
#8000000
1"
b00000000000 %
b00000000000 &
1'
b00000000000 +
b00000000000 ,
#16000000
0"
0'
#24000000
1"
1'
#32000000
0!
0"
0'
0(
#40000000
1"
1'
#48000000
0"
b00001110011 #
b11010101010 $
0'
b00001110011 )
b11010101010 *
#56000000
1"
1'
#64000000
0"
b00001110111 #
b11010100110 $
0'
b00001110111 )
b11010100110 *
#72000000
1"
1'
#80000000
0"
b00001110011 #
b11010111110 $
0'
b00001110011 )
b11010111110 *
#88000000
1"
1'
#96000000
0"
b00001101000 #
b11011110001 $
0'
b00001101000 )
b11011110001 *
#104000000
1"
1'
#112000000
0"
b00001011010 #
b11100110111 $
0'
b00001011010 )
b11100110111 *
#120000000
1"
1'
#128000000
0"
b00001001101 #
b11110000111 $
0'
b00001001101 )
b11110000111 *
#136000000
1"
1'
#144000000
0"
b00001000100 #
b11111011010 $
0'
b00001000100 )
b11111011010 *
#152000000
1"
1'
#160000000
0"
b00001000001 #
b00000100100 $
0'
b00001000001 )
b00000100100 *
#168000000
1"
1'
#176000000
0"
b00001000101 #
b00001011110 $
0'
b00001000101 )
b00001011110 *
#184000000
1"
1'
#192000000
0"
b00001010010 #
b00010000010 $
0'
b00001010010 )
b00010000010 *
#200000000
1"
1'
#208000000
0"
b00001100100 #
b00010001101 $
0'
b00001100100 )
b00010001101 *
#216000000
1"
b00001110011 %
b11010010101 &
1'
b00001110011 +
b11010010101 ,
#224000000
0"
b00001111100 #
b00001111101 $
0'
b00001111100 )
b00001111101 *
#232000000
1"
b00001101011 %
b11011000111 &
1'
b00001101011 +
b11011000111 ,
#240000000
0"
b00010010110 #
b00001011000 $
0'
b00010010110 )
b00001011000 *
#248000000
1"
b00001101110 %
b11011000010 &
1'
b00001101110 +
b11011000010 ,
#256000000
0"
b00010110001 #
b00000100000 $
0'
b00010110001 )
b00000100000 *
#264000000
1"
b00001100011 %
b11011110110 &
1'
b00001100011 +
b11011110110 ,
#272000000
0"
b00011001011 #
b11111011111 $
0'
b00011001011 )
b11111011111 *
#280000000
1"
b00001010110 %
b11100111100 &
1'
b00001010110 +
b11100111100 ,
#288000000
0"
b00011100010 #
b11110011011 $
0'
b00011100010 )
b11110011011 *
#296000000
1"
b00001001010 %
b11110001001 &
1'
b00001001010 +
b11110001001 ,
#304000000
0"
b00011110110 #
b11101011011 $
0'
b00011110110 )
b11101011011 *
#312000000
1"
b00001000011 %
b11111010111 &
1'
b00001000011 +
b11111010111 ,
#320000000
0"
b00100000111 #
b11100100111 $
0'
b00100000111 )
b11100100111 *
#328000000
1"
b00000111110 %
b00000011100 &
1'
b00000111110 +
b00000011100 ,
#336000000
0"
b00100010100 #
b11100000000 $
0'
b00100010100 )
b11100000000 *
#344000000
1"
b00001000100 %
b00001010101 &
1'
b00001000100 +
b00001010101 ,
#352000000
0"
b00100011110 #
b11011101010 $
0'
b00100011110 )
b11011101010 *
#360000000
1"
b00001001111 %
b00001111010 &
1'
b00001001111 +
b00001111010 ,
#368000000
0"
b00100100101 #
b11011100100 $
0'
b00100100101 )
b11011100100 *
#376000000
1"
b00001100010 %
b00010000101 &
1'
b00001100010 +
b00010000101 ,
#384000000
0"
b00100100111 #
b11011101011 $
0'
b00100100111 )
b11011101011 *
