VHDL/DPD.vhd
LIBRARY IEEE;
USE IEEE.STD_LOGIC_1164.ALL;
USE IEEE.NUMERIC_STD.ALL;
USE work.functions.ALL;

ENTITY DPD IS
    PORT (
        clk    : IN  STD_LOGIC;
        reset  : IN  STD_LOGIC;
        UR     : IN  STD_LOGIC_VECTOR(n_bits_resolution-1 DOWNTO 0);
        UI     : IN  STD_LOGIC_VECTOR(n_bits_resolution-1 DOWNTO 0);
        UR_out : OUT STD_LOGIC_VECTOR(n_bits_resolution-1 DOWNTO 0);
        UI_out : OUT STD_LOGIC_VECTOR(n_bits_resolution-1 DOWNTO 0)
    );
END ENTITY;

ARCHITECTURE rtl OF DPD IS

    SIGNAL delay_line : delay_line_t    := (OTHERS => zero_complex);
    SIGNAL mag2       : mag_array_t     := (OTHERS => 0);
    SIGNAL XX         : power_vector_t  := (OTHERS => zero_complex);
    SIGNAL multiplied : power_vector_t  := (OTHERS => zero_complex);

BEGIN

    --------------------------------------------------------------------
    -- 1. Delay line
    --------------------------------------------------------------------
    delay_process : PROCESS(clk)
        VARIABLE din        : complex_number;
        VARIABLE temp_delay : delay_line_t;
    BEGIN
        IF rising_edge(clk) THEN
            IF reset = '1' THEN
                delay_line <= (OTHERS => zero_complex);
            ELSE
                din.reall := clip_data(to_integer(signed(UR)));
                din.imag  := clip_data(to_integer(signed(UI)));

                temp_delay := delay_line;
                temp_delay(0) := din;

                FOR m IN 1 TO n_signals_used-1 LOOP
                    temp_delay(m) := delay_line(m-1);
                END LOOP;

                delay_line <= temp_delay;
            END IF;
        END IF;
    END PROCESS;

    --------------------------------------------------------------------
    -- 2. |x[n-m]|? usando o delay_line registrado anterior
    --------------------------------------------------------------------
    mag2_process : PROCESS(clk)
        VARIABLE temp_mag2 : mag_array_t;
    BEGIN
        IF rising_edge(clk) THEN
            IF reset = '1' THEN
                mag2 <= (OTHERS => 0);
            ELSE
                FOR m IN 0 TO n_signals_used-1 LOOP
                    temp_mag2(m) := calc_mag2(delay_line(m));
                END LOOP;
                mag2 <= temp_mag2;
            END IF;
        END IF;
    END PROCESS;

    --------------------------------------------------------------------
    -- 3. Gera??o compacta de XX igual ao Python mp_int_trunc
    -- Ordem: m=0 p=1..5, m=1 p=1..3, m=2 p=1
    -- Usa delay_line e mag2 REGISTRADOS do ciclo anterior.
    --------------------------------------------------------------------
    power_process : PROCESS(clk)
        VARIABLE temp_xx : power_vector_t;
        VARIABLE idx     : INTEGER;
        VARIABLE rr, ii  : INTEGER;
        VARIABLE A, B    : INTEGER;
        VARIABLE msq     : INTEGER;
        VARIABLE base    : complex_number;
    BEGIN
        IF rising_edge(clk) THEN
            IF reset = '1' THEN
                XX <= (OTHERS => zero_complex);
            ELSE
                temp_xx := (OTHERS => zero_complex);
                idx := 0;

                FOR m IN 0 TO n_signals_used - 1 LOOP
                    -- Igual ao Python: clip na entrada do atraso antes da recurs?o
                    A := clip_data(delay_line(m).reall);
                    B := clip_data(delay_line(m).imag);

                    -- Igual ao Python: modulo_square = readeq(A^2) + readeq(B^2)
                    msq := readeq(A * A) + readeq(B * B);

                    base.reall := A;
                    base.imag  := B;

                    -- Gera exatamente ordens(m) termos para este atraso
                    FOR p IN 0 TO poly_degree_per_delay(m) - 1 LOOP
                        IF p = 0 THEN
                            temp_xx(idx) := base;
                        ELSE
                            rr := readeq(base.reall * msq);
                            ii := readeq(base.imag  * msq);

                            base.reall := clip_data(rr);
                            base.imag  := clip_data(ii);

                            temp_xx(idx) := base;
                        END IF;

                        idx := idx + 1;
                    END LOOP;
                END LOOP;

                XX <= temp_xx;
            END IF;
        END IF;
    END PROCESS;

    --------------------------------------------------------------------
    -- 4. Multiplica??o compacta igual ao Python MultiplicadorMatrizes
    -- Usa XX REGISTRADO do ciclo anterior.
    --------------------------------------------------------------------
    mult_process : PROCESS(clk)
        VARIABLE temp_mult : power_vector_t;
    BEGIN
        IF rising_edge(clk) THEN
            IF reset = '1' THEN
                multiplied <= (OTHERS => zero_complex);
            ELSE
                temp_mult := (OTHERS => zero_complex);

                FOR k IN 0 TO n_total_terms - 1 LOOP
                    temp_mult(k) := cmul(coefficients(k), XX(k));
                END LOOP;

                multiplied <= temp_mult;
            END IF;
        END IF;
    END PROCESS;

    --------------------------------------------------------------------
    -- 5. Soma final igual ao Python:
    -- soma todos os termos e clipa s? no final.
    --------------------------------------------------------------------
    sum_process : PROCESS(clk)
        VARIABLE acc_re, acc_im : INTEGER;
    BEGIN
        IF rising_edge(clk) THEN
            IF reset = '1' THEN
                UR_out <= (OTHERS => '0');
                UI_out <= (OTHERS => '0');
            ELSE
                acc_re := 0;
                acc_im := 0;

                FOR k IN 0 TO n_total_terms - 1 LOOP
                    acc_re := acc_re + multiplied(k).reall;
                    acc_im := acc_im + multiplied(k).imag;
                END LOOP;

                UR_out <= STD_LOGIC_VECTOR(to_signed(clip_data(acc_re), n_bits_resolution));
                UI_out <= STD_LOGIC_VECTOR(to_signed(clip_data(acc_im), n_bits_resolution));
            END IF;
        END IF;
    END PROCESS;

END ARCHITECTURE;

tb_main.vhd
--------------------------------------------------------------------------------
LIBRARY ieee;
USE ieee.std_logic_1164.ALL;
  
ENTITY tb IS
END tb;
 
ARCHITECTURE behavior OF tb IS 
    CONSTANT n_bits_resolution : INTEGER := 9;
    CONSTANT n_bits_overflow : INTEGER := 8;
    CONSTANT n_signals_used : INTEGER := 2;
    CONSTANT n_polygnos_degree : INTEGER := 2;
    -- Component Declaration for the Unit Under Test (UUT)
    COMPONENT dpd
        PORT (
            reset : IN STD_LOGIC;
            clk : IN STD_LOGIC;
            UR : IN STD_LOGIC_VECTOR(n_bits_resolution - 1 DOWNTO 0);
            UI : IN STD_LOGIC_VECTOR(n_bits_resolution - 1 DOWNTO 0);
            UR_out : OUT STD_LOGIC_VECTOR(n_bits_resolution - 1 DOWNTO 0);
            UI_out : OUT STD_LOGIC_VECTOR(n_bits_resolution - 1 DOWNTO 0)
        );
    END COMPONENT;

    -- Signals for connecting to UUT
    SIGNAL reset : STD_LOGIC := '0';
    SIGNAL clk : STD_LOGIC := '0';
    SIGNAL UR : STD_LOGIC_VECTOR(n_bits_resolution - 1 DOWNTO 0) := (OTHERS => '0');
    SIGNAL UI : STD_LOGIC_VECTOR(n_bits_resolution - 1 DOWNTO 0) := (OTHERS => '0');
    SIGNAL UR_out : STD_LOGIC_VECTOR(n_bits_resolution - 1 DOWNTO 0) := (OTHERS => '0');
    SIGNAL UI_out : STD_LOGIC_VECTOR(n_bits_resolution - 1 DOWNTO 0);

    -- Clock period definition
    CONSTANT clk_period : TIME := 10 ns;
 
BEGIN
 
	-- Instantiate the Unit Under Test (UUT)
   uut: DPD PORT MAP (
          reset => reset,
          clk => clk,
          UR => UR,
          UI => UI,
          UR_out => UR_out,
          UI_out => UI_out
        );

   -- Clock process definitions
   clk_process :process
   begin
		clk <= '0';
		wait for clk_period/2;
		clk <= '1';
		wait for clk_period/2;
   end process;
 

   -- Stimulus process
   stim_proc: process
   begin		
      -- hold reset state for 100 ns.
      wait for 100 ns;	

      wait for clk_period*10;

      -- insert stimulus here 
      wait;
   end process;

      -- in process
   calc_proc: process
   begin		
      reset <= '1';
      wait for 2 * clk_period;	
      reset <= '0';
      WAIT FOR clk_period;
      
UR <= "000111101";
UI <= "010100000";
WAIT FOR clk_period;
UR <= "000011100";
UI <= "010100101";
WAIT FOR clk_period;
UR <= "111111001";
UI <= "010100001";
WAIT FOR clk_period;
UR <= "111011010";
UI <= "010010111";
WAIT FOR clk_period;
UR <= "110111101";
UI <= "010001000";
WAIT FOR clk_period;
UR <= "110100101";
UI <= "001110100";
WAIT FOR clk_period;
UR <= "110001111";
UI <= "001011110";
WAIT FOR clk_period;
UR <= "101111110";
UI <= "001001000";
WAIT FOR clk_period;
UR <= "101110000";
UI <= "000110101";
WAIT FOR clk_period;
UR <= "101100110";
UI <= "000100100";
WAIT FOR clk_period;
UR <= "101011111";
UI <= "000011010";
WAIT FOR clk_period;
UR <= "101011011";
UI <= "000010101";
WAIT FOR clk_period;
UR <= "101011010";
UI <= "000010111";
WAIT FOR clk_period;
UR <= "101011011";
UI <= "000011100";
WAIT FOR clk_period;
UR <= "101011100";
UI <= "000100110";
WAIT FOR clk_period;
UR <= "101011110";
UI <= "000101111";
WAIT FOR clk_period;
UR <= "101100000";
UI <= "000111001";
WAIT FOR clk_period;
UR <= "101100010";
UI <= "000111110";
WAIT FOR clk_period;
UR <= "101100001";
UI <= "000111111";
WAIT FOR clk_period;
UR <= "101011111";
UI <= "000111011";
WAIT FOR clk_period;
UR <= "101011010";
UI <= "000110010";
WAIT FOR clk_period;
UR <= "101010100";
UI <= "000100101";
WAIT FOR clk_period;
UR <= "101010000";
UI <= "000010110";
WAIT FOR clk_period;
UR <= "101001011";
UI <= "000001011";
WAIT FOR clk_period;
UR <= "101000111";
UI <= "000000011";
WAIT FOR clk_period;
UR <= "101001001";
UI <= "000000001";
WAIT FOR clk_period;
UR <= "101001111";
UI <= "000001000";
WAIT FOR clk_period;
UR <= "101011011";
UI <= "000011000";
WAIT FOR clk_period;
UR <= "101101101";
UI <= "000110001";
WAIT FOR clk_period;
UR <= "110000011";
UI <= "001010000";
WAIT FOR clk_period;
UR <= "110011110";
UI <= "001110010";
WAIT FOR clk_period;
UR <= "110111101";
UI <= "010010011";
WAIT FOR clk_period;
UR <= "111011011";
UI <= "010110001";
WAIT FOR clk_period;
UR <= "111111000";
UI <= "011000101";
WAIT FOR clk_period;
UR <= "000010011";
UI <= "011001011";
WAIT FOR clk_period;
UR <= "000101000";
UI <= "011000011";
WAIT FOR clk_period;
UR <= "000111000";
UI <= "010101100";
WAIT FOR clk_period;
UR <= "001000000";
UI <= "010000111";
WAIT FOR clk_period;
UR <= "001000001";
UI <= "001010101";
WAIT FOR clk_period;
UR <= "000111100";
UI <= "000011110";
WAIT FOR clk_period;
UR <= "000101111";
UI <= "111100100";
WAIT FOR clk_period;
UR <= "000011100";
UI <= "110101101";
WAIT FOR clk_period;
UR <= "000000110";
UI <= "110000000";
WAIT FOR clk_period;
UR <= "111101111";
UI <= "101011100";
WAIT FOR clk_period;
UR <= "111010110";
UI <= "101001010";
WAIT FOR clk_period;
UR <= "110111100";
UI <= "101001001";
WAIT FOR clk_period;
UR <= "110100011";
UI <= "101010101";
WAIT FOR clk_period;
UR <= "110001111";
UI <= "101110001";
WAIT FOR clk_period;
UR <= "101111101";
UI <= "110010110";
WAIT FOR clk_period;
UR <= "101101101";
UI <= "111000001";
WAIT FOR clk_period;

      -- insert stimulus here 
      wait;
   end process;
    
END;

VHDL/output.vcd
$date
  Thu Apr  2 15:02:41 2026
$end
$version
  GHDL v0
$end
$timescale
  1 fs
$end
$scope module standard $end
$upscope $end
$scope module textio $end
$upscope $end
$scope module std_logic_1164 $end
$upscope $end
$scope module numeric_std $end
$upscope $end
$scope module std_logic_textio $end
$upscope $end
$scope module env $end
$upscope $end
$scope module functions $end
$upscope $end
$scope module tb $end
$var reg 1 ! reset $end
$var reg 1 " clk $end
$var reg 11 # ur[10:0] $end
$var reg 11 $ ui[10:0] $end
$var reg 11 % ur_out[10:0] $end
$var reg 11 & ui_out[10:0] $end
$scope module uut $end
$var reg 1 ' clk $end
$var reg 1 ( reset $end
$var reg 11 ) ur[10:0] $end
$var reg 11 * ui[10:0] $end
$var reg 11 + ur_out[10:0] $end
$var reg 11 , ui_out[10:0] $end
$comment delay_line is not handled $end
$comment mag2 is not handled $end
$comment xx is not handled $end
$comment multiplied is not handled $end
$upscope $end
$upscope $end
$enddefinitions $end
#0
1!
0"
b00000000000 #
b00000000000 $
bUUUUUUUUUUU %
bUUUUUUUUUUU &
0'
1(
b00000000000 )
b00000000000 *
bUUUUUUUUUUU +
bUUUUUUUUUUU ,
#8000000
1"
b00000000000 %
b00000000000 &
1'
b00000000000 +
b00000000000 ,
#16000000
0"
0'
#24000000
1"
1'
#32000000
0!
0"
0'
0(
#40000000
1"
1'
#48000000
0"
b00001110011 #
b11010101010 $
0'
b00001110011 )
b11010101010 *
#56000000
1"
1'
#64000000
0"
b00001110111 #
b11010100110 $
0'
b00001110111 )
b11010100110 *
#72000000
1"
1'
#80000000
0"
b00001110011 #
b11010111110 $
0'
b00001110011 )
b11010111110 *
#88000000
1"
1'
#96000000
0"
b00001101000 #
b11011110001 $
0'
b00001101000 )
b11011110001 *
#104000000
1"
b00001110011 %
b11010010101 &
1'
b00001110011 +
b11010010101 ,
#112000000
0"
b00001011010 #
b11100110111 $
0'
b00001011010 )
b11100110111 *
#120000000
1"
b00001101011 %
b11011000111 &
1'
b00001101011 +
b11011000111 ,
#128000000
0"
b00001001101 #
b11110000111 $
0'
b00001001101 )
b11110000111 *
#136000000
1"
b00001101110 %
b11011000010 &
1'
b00001101110 +
b11011000010 ,
#144000000
0"
b00001000100 #
b11111011010 $
0'
b00001000100 )
b11111011010 *
#152000000
1"
b00001100011 %
b11011110110 &
1'
b00001100011 +
b11011110110 ,
#160000000
0"
b00001000001 #
b00000100100 $
0'
b00001000001 )
b00000100100 *
#168000000
1"
b00001010110 %
b11100111100 &
1'
b00001010110 +
b11100111100 ,
#176000000
0"
b00001000101 #
b00001011110 $
0'
b00001000101 )
b00001011110 *
#184000000
1"
b00001001010 %
b11110001001 &
1'
b00001001010 +
b11110001001 ,
#192000000
0"
b00001010010 #
b00010000010 $
0'
b00001010010 )
b00010000010 *
#200000000
1"
b00001000011 %
b11111010111 &
1'
b00001000011 +
b11111010111 ,
#208000000
0"
b00001100100 #
b00010001101 $
0'
b00001100100 )
b00010001101 *
#216000000
1"
b00000111110 %
b00000011100 &
1'
b00000111110 +
b00000011100 ,
#224000000
0"
b00001111100 #
b00001111101 $
0'
b00001111100 )
b00001111101 *
#232000000
1"
b00001000100 %
b00001010101 &
1'
b00001000100 +
b00001010101 ,
#240000000
0"
b00010010110 #
b00001011000 $
0'
b00010010110 )
b00001011000 *
#248000000
1"
b00001001111 %
b00001111010 &
1'
b00001001111 +
b00001111010 ,
#256000000
0"
b00010110001 #
b00000100000 $
0'
b00010110001 )
b00000100000 *
#264000000
1"
b00001100010 %
b00010000101 &
1'
b00001100010 +
b00010000101 ,
#272000000
0"
b00011001011 #
b11111011111 $
0'
b00011001011 )
b11111011111 *
#280000000
1"
b00001110111 %
b00001110111 &
1'
b00001110111 +
b00001110111 ,
#288000000
0"
b00011100010 #
b11110011011 $
0'
b00011100010 )
b11110011011 *
#296000000
1"
b00010010010 %
b00001010011 &
1'
b00010010010 +
b00001010011 ,
#304000000
0"
b00011110110 #
b11101011011 $
0'
b00011110110 )
b11101011011 *
#312000000
1"
b00010101001 %
b00000011111 &
1'
b00010101001 +
b00000011111 ,
#320000000
0"
b00100000111 #
b11100100111 $
0'
b00100000111 )
b11100100111 *
#328000000
1"
b00011000101 %
b11111100010 &
1'
b00011000101 +
b11111100010 ,
#336000000
0"
b00100010100 #
b11100000000 $
0'
b00100010100 )
b11100000000 *
#344000000
1"
b00011011011 %
b11110011101 &
1'
b00011011011 +
b11110011101 ,
#352000000
0"
b00100011110 #
b11011101010 $
0'
b00100011110 )
b11011101010 *
#360000000
1"
b00011110010 %
b11101011110 &
1'
b00011110010 +
b11101011110 ,
#368000000
0"
b00100100101 #
b11011100100 $
0'
b00100100101 )
b11011100100 *
#376000000
1"
b00100000011 %
b11100101000 &
1'
b00100000011 +
b11100101000 ,
#384000000
0"
b00100100111 #
b11011101011 $
0'
b00100100111 )
b11011101011 *
#392000000
1"
b00100010010 %
b11100000010 &
1'
b00100010010 +
b11100000010 ,
#400000000
0"
b00100100101 #
b11011111101 $
0'
b00100100101 )
b11011111101 *
#408000000
1"
b00100011011 %
b11011101011 &
1'
b00100011011 +
b11011101011 ,
#416000000
0"
b00100011100 #
b11100010101 $
0'
b00100011100 )
b11100010101 *
#424000000
1"
b00100100011 %
b11011100011 &
1'
b00100100011 +
b11011100011 ,
#432000000
0"
b00100001100 #
b11100101111 $
0'
b00100001100 )
b11100101111 *
#440000000
1"
b11011101011 &
1'
b11011101011 ,
#448000000
0"
b00011110101 #
b11101001011 $
0'
b00011110101 )
b11101001011 *
#456000000
1"
b00100100010 %
b11011111111 &
1'
b00100100010 +
b11011111111 ,
#464000000
0"
b00011010111 #
b11101100111 $
0'
b00011010111 )
b11101100111 *
#472000000
1"
b00100010110 %
b11100010110 &
1'
b00100010110 +
b11100010110 ,
#480000000
0"
b00010110010 #
b11110000100 $
0'
b00010110010 )
b11110000100 *
#488000000
1"
b00100000110 %
b11100110010 &
1'
b00100000110 +
b11100110010 ,
#496000000
0"
b00010001000 #
b11110100011 $
0'
b00010001000 )
b11110100011 *
#504000000
1"
b00011110000 %
b11101001100 &
1'
b00011110000 +
b11101001100 ,
#512000000
0"
b00001011100 #
b11111001000 $
0'
b00001011100 )
b11111001000 *
#520000000
1"
b00011010010 %
b11101101001 &
1'
b00011010010 +
b11101101001 ,
#528000000
0"
b00000110001 #
b11111110100 $
0'
b00000110001 )
b11111110100 *
#536000000
1"
b00010101110 %
b11110001000 &
1'
b00010101110 +
b11110001000 ,
#544000000
0"
b00000001011 #
b00000101010 $
0'
b00000001011 )
b00000101010 *
#552000000
1"
b00010000100 %
b11110100101 &
1'
b00010000100 +
b11110100101 ,
#560000000
0"
b11111101010 #
b00001101001 $
0'
b11111101010 )
b00001101001 *
#568000000
1"
b00001011011 %
b11111001001 &
1'
b00001011011 +
b11111001001 ,
#576000000
0"
b11111010010 #
b00010110000 $
0'
b11111010010 )
b00010110000 *
#584000000
1"
b00000110001 %
b11111110011 &
1'
b00000110001 +
b11111110011 ,
#592000000
0"
b11111000001 #
b00011111011 $
0'
b11111000001 )
b00011111011 *
#600000000
1"
b00000001101 %
b00000100101 &
1'
b00000001101 +
b00000100101 ,
#608000000
0"
b11110110111 #
b00101000100 $
0'
b11110110111 )
b00101000100 *
#616000000
1"
b11111110000 %
b00001100010 &
1'
b11111110000 +
b00001100010 ,
#624000000
0"
b11110110010 #
b00110000100 $
0'
b11110110010 )
b00110000100 *
#632000000
1"
b11111010111 %
b00010101000 &
1'
b11111010111 +
b00010101000 ,
#640000000
0"
b11110101110 #
b00110110101 $
0'
b11110101110 )
b00110110101 *
#648000000
1"
b11111001000 %
b00011110110 &
1'
b11111001000 +
b00011110110 ,
#656000000
0"
b11110101000 #
b00111010000 $
0'
b11110101000 )
b00111010000 *
#664000000
1"
b11110111010 %
b00101000010 &
1'
b11110111010 +
b00101000010 ,
#672000000
0"
b11110011101 #
b00111001111 $
0'
b11110011101 )
b00111001111 *
#680000000
1"
b11110110101 %
b00110000011 &
1'
b11110110101 +
b00110000011 ,
#688000000
0"
b11110001010 #
b00110110000 $
0'
b11110001010 )
b00110110000 *
#696000000
1"
b11110110000 %
b00110110110 &
1'
b11110110000 +
b00110110110 ,
#704000000
0"
b11101110000 #
b00101110011 $
0'
b11101110000 )
b00101110011 *
#712000000
1"
b11110101010 %
b00111010000 &
1'
b11110101010 +
b00111010000 ,
#720000000
0"
b11101001110 #
b00100011101 $
0'
b11101001110 )
b00100011101 *
#728000000
1"
b11110100000 %
b00111001110 &
1'
b11110100000 +
b00111001110 ,
#736000000
0"
b11100101000 #
b00010110010 $
0'
b11100101000 )
b00010110010 *
#744000000
1"
b11110001101 %
b00110101101 &
1'
b11110001101 +
b00110101101 ,
#752000000
0"
b11100000000 #
b00000111101 $
0'
b11100000000 )
b00000111101 *
#760000000
1"
b11101110011 %
b00101101101 &
1'
b11101110011 +
b00101101101 ,
#768000000
0"
b11011011100 #
b11111000110 $
0'
b11011011100 )
b11111000110 *
#776000000
1"
b11101010011 %
b00100011000 &
1'
b11101010011 +
b00100011000 ,
#784000000
0"
b11011000000 #
b11101011001 $
0'
b11011000000 )
b11101011001 *
#792000000
1"
b11100101110 %
b00010110000 &
1'
b11100101110 +
b00010110000 ,
#800000000
0"
b11010101110 #
b11011111110 $
0'
b11010101110 )
b11011111110 *
#808000000
1"
b11100000100 %
b00000111111 &
1'
b11100000100 +
b00000111111 ,
#816000000
0"
b11010101011 #
b11010111011 $
0'
b11010101011 )
b11010111011 *
#824000000
1"
b11011011111 %
b11111010000 &
1'
b11011011111 +
b11111010000 ,
#832000000
0"
b11010110110 #
b11010010010 $
0'
b11010110110 )
b11010010010 *
#840000000
1"
b11010111110 %
b11101011110 &
1'
b11010111110 +
b11101011110 ,
#848000000
0"
b11011001110 #
b11010000100 $
0'
b11011001110 )
b11010000100 *
#856000000
1"
b11010101001 %
b11100000010 &
1'
b11010101001 +
b11100000010 ,
#864000000
0"
b11011110000 #
b11010001101 $
0'
b11011110000 )
b11010001101 *
#872000000
1"
b11010100111 %
b11010111101 &
1'
b11010100111 +
b11010111101 ,
#880000000
0"
b11100011000 #
b11010100101 $
0'
b11100011000 )
b11010100101 *
#888000000
1"
b11010110101 %
b11010010101 &
1'
b11010110101 +
b11010010101 ,
#896000000
0"
b11101000010 #
b11011000100 $
0'
b11101000010 )
b11011000100 *
#904000000
1"
b11011001111 %
b11010001000 &
1'
b11011001111 +
b11010001000 ,
#912000000
0"
b11101101001 #
b11011100010 $
0'
b11101101001 )
b11011100010 *
#920000000
1"
b11011110000 %
b11010010001 &
1'
b11011110000 +
b11010010001 ,
#928000000
0"
b11110001010 #
b11011110111 $
0'
b11110001010 )
b11011110111 *
#936000000
1"
b11100011000 %
b11010101011 &
1'
b11100011000 +
b11010101011 ,
#944000000
0"
b11110100011 #
b11011111110 $
0'
b11110100011 )
b11011111110 *
#952000000
1"
b11101000011 %
b11011001001 &
1'
b11101000011 +
b11011001001 ,
#960000000
0"
b11110110100 #
b11011110101 $
0'
b11110110100 )
b11011110101 *
#968000000
1"
b11101101000 %
b11011100110 &
1'
b11101101000 +
b11011100110 ,
#976000000
0"
b11110111110 #
b11011100000 $
0'
b11110111110 )
b11011100000 *
#984000000
1"
b11110001010 %
b11011111011 &
1'
b11110001010 +
b11011111011 ,
#992000000
0"
b11111000101 #
b11011000101 $
0'
b11111000101 )
b11011000101 *
#1000000000
1"
b11110100010 %
b11100000001 &
1'
b11110100010 +
b11100000001 ,
#1008000000
0"
b11111001100 #
b11010101011 $
0'
b11111001100 )
b11010101011 *
#1016000000
1"
b11110110011 %
b11011110111 &
1'
b11110110011 +
b11011110111 ,
#1024000000
0"
b11111011000 #
b11010011110 $
0'
b11111011000 )
b11010011110 *
#1032000000
1"
b11110111101 %
b11011100010 &
1'
b11110111101 +
b11011100010 ,
#1040000000
0"
b11111101010 #
b11010100111 $
0'
b11111101010 )
b11010100111 *
#1048000000
1"
b11111000100 %
b11011001000 &
1'
b11111000100 +
b11011001000 ,
#1056000000
0"
b00000000110 #
b11011001101 $
0'
b00000000110 )
b11011001101 *
#1064000000
1"
b11111001100 %
b11010101111 &
1'
b11111001100 +
b11010101111 ,
#1072000000
0"
b00000101010 #
b11100010100 $
0'
b00000101010 )
b11100010100 *
#1080000000
1"
b11111010110 %
b11010100001 &
1'
b11111010110 +
b11010100001 ,
#1088000000
0"
b00001010110 #
b11101111011 $
0'
b00001010110 )
b11101111011 *
#1096000000
1"
b11111101001 %
b11010101101 &
1'
b11111101001 +
b11010101101 ,
#1104000000
0"
b00010000011 #
b11111111010 $
0'
b00010000011 )
b11111111010 *
#1112000000
1"
b00000000010 %
b11011010100 &
1'
b00000000010 +
b11011010100 ,
#1120000000
0"
b00010101111 #
b00010001000 $
0'
b00010101111 )
b00010001000 *
#1128000000
1"
b00000101000 %
b11100011100 &
1'
b00000101000 +
b11100011100 ,
#1136000000
0"
b00011010010 #
b00100010101 $
0'
b00011010010 )
b00100010101 *
#1144000000
1"
b00001010010 %
b11101111110 &
1'
b00001010010 +
b11101111110 ,
#1152000000
0"
b00011101000 #
b00110010001 $
0'
b00011101000 )
b00110010001 *
#1160000000
1"
b00001111101 %
b11111110100 &
1'
b00001111101 +
b11111110100 ,
#1168000000
0"
b00011101100 #
b00111101101 $
0'
b00011101100 )
b00111101101 *
#1176000000
1"
b00010101100 %
b00001111100 &
1'
b00010101100 +
b00001111100 ,
#1184000000
0"
b00011011011 #
b01000011100 $
0'
b00011011011 )
b01000011100 *
#1192000000
1"
b00011010101 %
b00100010000 &
1'
b00011010101 +
b00100010000 ,
#1200000000
0"
b00010110110 #
b01000010111 $
0'
b00010110110 )
b01000010111 *
#1208000000
1"
b00011101101 %
b00110010011 &
1'
b00011101101 +
b00110010011 ,
#1216000000
0"
b00001111111 #
b00111011101 $
0'
b00001111111 )
b00111011101 *
#1224000000
1"
b00011101111 %
b00111110011 &
1'
b00011101111 +
b00111110011 ,
#1232000000
0"
b00000111001 #
b00101110011 $
0'
b00000111001 )
b00101110011 *
#1240000000
1"
b00011011000 %
b01000011101 &
1'
b00011011000 +
b01000011101 ,
#1248000000
0"
b11111101011 #
b00011100110 $
0'
b11111101011 )
b00011100110 *
#1256000000
1"
b00010101111 %
b01000010100 &
1'
b00010101111 +
b01000010100 ,
#1264000000
0"
b11110011100 #
b00001000101 $
0'
b11110011100 )
b00001000101 *
#1272000000
1"
b00001111011 %
b00111010010 &
1'
b00001111011 +
b00111010010 ,
#1280000000
0"
b11101010010 #
b11110100100 $
0'
b11101010010 )
b11110100100 *
#1288000000
1"
b00000110111 %
b00101100101 &
1'
b00000110111 +
b00101100101 ,
#1296000000
0"
b11100010110 #
b11100010101 $
0'
b11100010110 )
b11100010101 *
#1304000000
1"
b11111101111 %
b00011011100 &
1'
b11111101111 +
b00011011100 ,
#1312000000
0"
b11011101011 #
b11010100111 $
0'
b11011101011 )
b11010100111 *
#1320000000
1"
b11110100011 %
b00001001001 &
1'
b11110100011 +
b00001001001 ,
#1328000000
0"
b11011011000 #
b11001100101 $
0'
b11011011000 )
b11001100101 *
#1336000000
1"
b11101011001 %
b11110110010 &
1'
b11101011001 +
b11110110010 ,
#1344000000
0"
b11011011110 #
b11001010100 $
0'
b11011011110 )
b11001010100 *
#1352000000
1"
b11100010100 %
b11100011101 &
1'
b11100010100 +
b11100011101 ,
#1360000000
0"
b11011111101 #
b11001101111 $
0'
b11011111101 )
b11001101111 *
#1368000000
1"
b11011100110 %
b11010101001 &
1'
b11011100110 +
b11010101001 ,
#1376000000
0"
b11100110101 #
b11010101111 $
0'
b11100110101 )
b11010101111 *
#1384000000
1"
b11011010111 %
b11001100110 &
1'
b11011010111 +
b11001100110 ,
#1392000000
0"
b11110000001 #
b11100000110 $
0'
b11110000001 )
b11100000110 *
#1400000000
1"
b11011011110 %
b11001010111 &
1'
b11011011110 +
b11001010111 ,
#1408000000
0"
b11111011110 #
b11101100010 $
0'
b11111011110 )
b11101100010 *
#1416000000
1"
b11011111111 %
b11001110101 &
1'
b11011111111 +
b11001110101 ,
#1424000000
0"
b00001000110 #
b11110110100 $
0'
b00001000110 )
b11110110100 *
#1432000000
1"
b11100111010 %
b11010111010 &
1'
b11100111010 +
b11010111010 ,
#1440000000
0"
b00010110011 #
b11111101110 $
0'
b00010110011 )
b11111101110 *
#1448000000
1"
b11110000100 %
b11100001111 &
1'
b11110000100 +
b11100001111 ,
#1456000000
0"
b00100011110 #
b00000000111 $
0'
b00100011110 )
b00000000111 *
#1464000000
1"
b11111011110 %
b11101100110 &
1'
b11111011110 +
b11101100110 ,
#1472000000
0"
b00101111111 #
b11111111010 $
0'
b00101111111 )
b11111111010 *
#1480000000
1"
b00000111111 %
b11110110000 &
1'
b00000111111 +
b11110110000 ,
#1488000000
0"
b00111010001 #
b11111001011 $
0'
b00111010001 )
b11111001011 *
#1496000000
1"
b00010101010 %
b11111101000 &
1'
b00010101010 +
b11111101000 ,
#1504000000
0"
b01000001110 #
b11110000001 $
0'
b01000001110 )
b11110000001 *
#1512000000
1"
b00100011001 %
b11111111111 &
1'
b00100011001 +
b11111111111 ,
#1520000000
0"
b01000101111 #
b11100101001 $
0'
b01000101111 )
b11100101001 *
#1528000000
1"
b00101111111 %
b11111110111 &
1'
b00101111111 +
b11111110111 ,
#1536000000
0"
b01000110010 #
b11011010000 $
0'
b01000110010 )
b11011010000 *
#1544000000
1"
b00111010011 %
b11111000100 &
1'
b00111010011 +
b11111000100 ,
#1552000000
0"
b01000010101 #
b11010000100 $
0'
b01000010101 )
b11010000100 *
#1560000000
1"
b01000010011 %
b11101111101 &
1'
b01000010011 +
b11101111101 ,
#1568000000
0"
b00111011000 #
b11001010000 $
0'
b00111011000 )
b11001010000 *
#1576000000
1"
b01000110101 %
b11100101000 &
1'
b01000110101 +
b11100101000 ,
#1584000000
0"
b00101111110 #
b11000111011 $
0'
b00101111110 )
b11000111011 *
#1592000000
1"
b01000111001 %
b11011010101 &
1'
b01000111001 +
b11011010101 ,
#1600000000
0"
b00100001101 #
b11001001001 $
0'
b00100001101 )
b11001001001 *
#1608000000
1"
b01000100000 %
b11010001100 &
1'
b01000100000 +
b11010001100 ,
#1616000000
0"
b00010001101 #
b11001110101 $
0'
b00010001101 )
b11001110101 *
#1624000000
1"
b00111100000 %
b11001011000 &
1'
b00111100000 +
b11001011000 ,
#1632000000
0"
b00000001000 #
b11010111011 $
0'
b00000001000 )
b11010111011 *
#1640000000
1"
b00101111101 %
b11001000001 &
1'
b00101111101 +
b11001000001 ,
#1648000000
0"
b11110001000 #
b11100001111 $
0'
b11110001000 )
b11100001111 *
#1656000000
1"
b00100000100 %
b11001010010 &
1'
b00100000100 +
b11001010010 ,
#1664000000
0"
b11100011000 #
b11101100110 $
0'
b11100011000 )
b11101100110 *
#1672000000
1"
b00010000110 %
b11001111111 &
1'
b00010000110 +
b11001111111 ,
#1680000000
0"
b11011000001 #
b11110110111 $
0'
b11011000001 )
b11110110111 *
#1688000000
1"
b00000000110 %
b11011001000 &
1'
b00000000110 +
b11011001000 ,
